{
  "perasha": "פרשת פינחס",
  "chapter": 28,
  "verse": 22,
  "verse_text_hebrew": "וּשְׂעִ֥יר חַטָּ֖את אֶחָ֑ד לְכַפֵּ֖ר עֲלֵיכֶֽם׃",
  "ref_he": "במדבר כ״ח:כ״ב",
  "source_url": "https://www.sefaria.org/Numbers.28.22",
  "commentaries": [
    {
      "commentator_name": "ביאור שטיינזלץ",
      "commentary_text": "וּשְׂעִיר חַטָּאת אֶחָד לְכַפֵּר עֲלֵיכֶם, שמא טימאתם שלא בכוונה את המקדש במשך השנה.",
      "source_url": "https://www.sefaria.org/Steinsaltz_on_Numbers_28:22"
    },
    {
      "commentator_name": "אבן עזרא",
      "commentary_text": "ושעיר חטאת. כמו שעיר עזים והוא דרך קצרה והנה לא הזכיר עולות בשבעת ימי הפסח כאשר לא הזכיר עולת התנופה ואנו צריכין לקבלה כי פסוק שבת בשבתו אמר על עולת התמיד:",
      "source_url": "https://www.sefaria.org/Ibn_Ezra_on_Numbers_28:22:1"
    },
    {
      "commentator_name": "העמק דבר",
      "commentary_text": "לכפר עליכם. ביארנו לעיל ט״ו שאגב מרומז כפרה על סקבא דשתא ריגלא:",
      "source_url": "https://www.sefaria.org/Haamek_Davar_on_Numbers_28:22:1"
    }
  ]
}