{
  "perasha": "פרשת פינחס",
  "chapter": 29,
  "verse": 5,
  "verse_text_hebrew": "וּשְׂעִיר־עִזִּ֥ים אֶחָ֖ד חַטָּ֑את לְכַפֵּ֖ר עֲלֵיכֶֽם׃",
  "ref_he": "במדבר כ״ט:ה׳",
  "source_url": "https://www.sefaria.org/Numbers.29.5",
  "commentaries": [
    {
      "commentator_name": "ביאור שטיינזלץ",
      "commentary_text": "וּשְׂעִיר עִזִּים אֶחָד חַטָּאת, לְכַפֵּר עֲלֵיכֶם.",
      "source_url": "https://www.sefaria.org/Steinsaltz_on_Numbers_29:5"
    },
    {
      "commentator_name": "שפתי כהן",
      "commentary_text": "שעיר עזים אחד חטאת. לא אמר ושעיר, כמ\"ש בשאר שאמר ושעיר בוא\"ו, וכן לא אמר לחטאת אלא חטאת, וכן לא אמר לכפר עליכם כמ\"ש בפסח ובחג השבועות ובראש השנה. ועוד שעיר זה למה, כבר נתנו לו שעיר אחד שעלה לו הגורל ונתרצה והלך לו. אלא שעיר זה היה קרב עם קרבן מוסף לומר שהוא תוספת חטוי ודכוי, לא שהיה בו צורך חטוי, כי א\"כ היל\"ל לחטאת, אלא אמר חטאת כל דהו הואיל ובכל המוספין של שאר המועדים היה קרב עמהם שעיר גם במוסף זה, ולזה היה נעשה בחוץ, כמ\"ש הרמב\"ם ז\"ל בהלכות יוה\"כ, שכתב היה נעשה בחוץ והיה נאכל בערב, נאכל בחוץ בלא פחד, לזה לא נאמר בו לכפר, כי כבר נתכפר פניו בשעיר של גורל וכן בכל קרבן מוסף של שמונה ימי החג לא נאמר בהם לכפר, וכן לא נאמר בהם לחטאת, אלא חטאת, לפי שבאלו הימים הם ימי שמחה והנחה למדינות עשה, שנותנין חלק לע' שרים, ואין שום מערער ואין שטן ואין פגע רע, ולזה אנו יושבין בסוכה בחוץ בלי פחד, כי הם ימי שמחה ולזה נכפלה השמחה בזה החג. וכן אמרו בזוהר בסעודתא עילאי דעביד ליה, האי רחימוי דמלכא ידע דמלכא אתרעי ביה, אמר מלכא השתא אנא בעי למחדי עם רחימאי ודחילנא דכד אנא בסעודתא עם רחימאי יעלון כל אינון קסטורי ממנן ויתבון עמנא לפתורא למסעד סעודתא דחדוה עם רחימאי, מה עבד אקדים ההוא רחימוי קוסטורין דירוקי ובשרא דתורי ואקריב קמייהו דאינון קסטורי ממנן למיכל, לבתר יתיב מלכא עם רחימוי לההיא סעודתא עילאה (פירוש מעולה) מכל עידונין דעלמא ואחדי מלכא עם רחימוי בלחודוהי ולא אתערבון אחרנין בינייהו, כך ישראל עם קוב\"ה, בגין כך כתיב ביום השמיני עצרת תהיה לכם, ע\"כ:",
      "source_url": "https://www.sefaria.org/Siftei_Kohen_on_Torah,_Numbers_29:5:1"
    },
    {
      "commentator_name": "מנחת שי",
      "commentary_text": "עזים. במירכא לא בתביר:",
      "source_url": "https://www.sefaria.org/Minchat_Shai_on_Torah,_Numbers_29:5:1"
    }
  ]
}