{
  "perasha": "פרשת בלק",
  "chapter": 22,
  "verse": 23,
  "verse_text_hebrew": "וַתֵּ֣רֶא הָאָתוֹן֩ אֶת־מַלְאַ֨ךְ יְהֹוָ֜ה נִצָּ֣ב בַּדֶּ֗רֶךְ וְחַרְבּ֤וֹ שְׁלוּפָה֙ בְּיָד֔וֹ וַתֵּ֤ט הָֽאָתוֹן֙ מִן־הַדֶּ֔רֶךְ וַתֵּ֖לֶךְ בַּשָּׂדֶ֑ה וַיַּ֤ךְ בִּלְעָם֙ אֶת־הָ֣אָת֔וֹן לְהַטֹּתָ֖הּ הַדָּֽרֶךְ׃",
  "ref_he": "במדבר כ״ב:כ״ג",
  "source_url": "https://www.sefaria.org/Numbers.22.23",
  "commentaries": [
    {
      "commentator_name": "רמב\"ן",
      "commentary_text": "וַתֵּרֶא הָאָתוֹן אֶת מַלְאַךְ ה' – מַלְאֲכֵי הַשֵּׁם הַשְּׂכָלִים הַנִּבְדָּלִים לֹא יֵרָאוּ לְחוּשׁ הָעֵינַיִם, כִּי אֵינָם גּוּף נִתְפָּשׂ בַּמַּרְאֶה. וְכַאֲשֶׁר יֵרָאוּ לַנְּבִיאִים אוֹ לְאַנְשֵׁי הָרוּחַ הַקֹּדֶשׁ כְּדָנִיֵּאל, יַשִּׂיגוּ אוֹתָם בְּמַרְאוֹת הַנֶּפֶשׁ הַמַּשְׂכֶּלֶת כַּאֲשֶׁר תַּגִּיעַ לְמַעֲלַת הַנְּבוּאָה אוֹ לְמַדְרֵגָה שֶׁתַּחְתֶּיהָ, אֲבָל שֶׁיּוּשְׂגוּ לְעֵינֵי הַבְּהֵמָה אִי אֶפְשָׁר. עַל כֵּן תּוּכַל לְפָרֵשׁ וַתֵּרֶא הָאָתוֹן כִּי הִרְגִּישָׁה בְּדָבָר מַפְחִיד אוֹתָהּ מִלַּעֲבֹר, וְהוּא הַמַּלְאָךְ אֲשֶׁר יָצָא לְשָׂטָן, כְּעִנְיַן ״וְלִבִּי רָאָה הַרְבֵּה חָכְמָה וָדָעַת״ (קהלת א, טז), שֶׁיֵּאָמֵר עַל הַהַשָּׂגָה לֹא עַל הָרְאוּת. וְכַאֲשֶׁר אֵרַע בָּהּ הַנֵּס וְשָׂם לָהּ הַבּוֹרֵא הַדִּבּוּר, אָמְרָה לְבִלְעָם ״הַהַסְכֵּן הִסְכַּנְתִּי לַעֲשׂוֹת לְךָ כֹּה״ (במדבר כ״ב:ל׳), אֲבָל לֹא יָדְעָה לָמָּה עָשְׂתָה עַתָּה כֵּן, כִּי לְאָנְסָהּ נַעֲשָׂה בָּהּ כָּךְ. וּלְפִיכָךְ לֹא אָמְרָה לוֹ, הִנֵּה מַלְאַךְ הַשֵּׁם עוֹמֵד לְנֶגְדִּי וְחַרְבּוֹ שְׁלוּפָה בְּיָדוֹ, כִּי לֹא עָלְתָה הַשָּׂגָתָהּ לָדַעַת זֶה כְּלָל. וְאָמַר ״וַתֵּרֶא אֶת מַלְאַךְ ה' וְחַרְבּוֹ שְׁלוּפָה בְּיָדוֹ״ - לֹא שֶׁתִּרְאֶה חֶרֶב אַף כִּי מַלְאָךְ, אֲבָל יִרְמֹז הַכָּתוּב כִּי מִפְּנֵי הֱיוֹת הַמַּלְאָךְ נָכוֹן לְהַכּוֹת בָּהּ, חָרְדָה חֲרָדָה גְדוֹלָה, נִדְמֶה לָהּ כְּאִלּוּ בָּאִים לִשְׁחֹט אוֹתָהּ. וְאִם נֹאמַר כִּי הַמַּלְאָכִים הַנִּרְאִים בִּדְמוּת אֲנָשִׁים כַּאֲשֶׁר הִזְכַּרְתִּי בְּפָרָשַׁת וַיֵּרָא (בראשית יח ב) יוּשְׂגוּ אַף לְעֵינֵי הַבְּהֵמוֹת, אִם כֵּן אֵיךְ לֹא יִרְאֶנּוּ בִלְעָם וְלֹא הֻכָּה בְּסַנְוֵרִים? אֲבָל יִתָּכֵן שֶׁהוֹסִיף בְּהַשָּׂגַת עֵינֶיהָ מִי שֶׁהוֹסִיף בָּהּ הַדִּבּוּר, וְרָאֲתָה כְּאָדָם. וְלֹא הִזְכִּיר בָּהּ הַכָּתוּב \"וַיְגַל הַשֵּׁם עֵינֵי הָאָתוֹן\" כַּאֲשֶׁר הִזְכִּיר בַּאֲדוֹנֶיהָ (במדבר כ״ב:ל״א), כִּי הָעִנְיָן כֻּלּוֹ בָּאָתוֹן נֵס גָּדוֹל כִּבְרִיאָה חֲדָשָׁה בַּנִּבְרָאִים בֵּין הַשְּׁמָשׁוֹת, וְאֵינוֹ נִקְרָא גִּלּוּי עֵינַיִם בִּלְבַד. אֲבָל רַבּוֹתֵינוּ (אבות פ״ה מ״ו) לֹא יַזְכִּירוּ בַּנִּסִּים רַק פְּתִיחַת פִּיהָ. וְטַעַם הַנֵּס הַזֶּה לְהַרְאוֹת לְבִלְעָם ״מִי שָׂם פֶּה לָאָדָם אוֹ מִי יָשׂוּם אִלֵּם״, לְהוֹדִיעוֹ כִּי הַשֵּׁם פּוֹתֵחַ פִּי הַנֶּאֱלָמִים, וְכָל שֶׁכֵּן שֶׁיַּאֲלִם פִּי הַמְדַבְּרִים, גַּם יָשִׂים בְּפִיהֶם דְּבָרִים לְדַבֵּר כִּרְצוֹנוֹ, כִּי הַכֹּל בְּיָדוֹ. וּלְהַזְהִירוֹ שֶׁלֹּא יֵלֵךְ אַחַר נַחַשׁ וְקֶסֶם וִיקַלְּלֵם בָּהֶם, כִּי מְנַחֵשׁ וְקוֹסֵם הָיָה:",
      "source_url": "https://www.sefaria.org/Ramban_on_Numbers_22:23:1"
    },
    {
      "commentator_name": "רש\"י",
      "commentary_text": "ותרא האתון. וְהוּא לֹא רָאָה שֶׁנָּתַן הַקָּבָּ\"ה רְשׁוּת לַבְּהֵמָה לִרְאוֹת יוֹתֵר מִן הָאָדָם, שֶׁמִּתוֹךְ שֶׁיֵּשׁ בּוֹ דַּעַת, תִּטָּרֵף דַּעְתּוֹ כְּשֶׁיִּרְאֶה מַזִּיקִין:",
      "source_url": "https://www.sefaria.org/Rashi_on_Numbers_22:23:1"
    },
    {
      "commentator_name": "רש\"י",
      "commentary_text": "וחרבו שלופה בידו. אָמַר, רָשָׁע זֶה הִנִּיחַ כְּלִי אֻמָּנוּתוֹ, שֶׁכְּלִי זֵינָן שֶׁל אֻמּוֹת הָעוֹלָם בַּחֶרֶב, וְהוּא בָא עֲלֵיהֶם בְּפִיו שֶׁהוּא אֻמָּנוּת שֶׁלָּהֶם, אַף אֲנִי אֶתְפֹּשׂ אֶת שֶׁלּוֹ וְאָבֹא עָלָיו בְּאֻמָּנוּתוֹ, וְכֵן סוֹפוֹ — \"וְאֵת בִּלְעָם בֶּן בְּעוֹר הָרְגוּ בֶחָרֶב\" (במדבר ל\"א):",
      "source_url": "https://www.sefaria.org/Rashi_on_Numbers_22:23:2"
    },
    {
      "commentator_name": "ספורנו",
      "commentary_text": "וַתֵּלֶךְ בַּשָּׂדֶה. וְאָז עָזַב שְׁנֵי נְעָרָיו וְשָׂרֵי מוֹאָב, וּבְכֵן לֹא הִרְגִּישׁוּ עִנְיָנוֹ בְּעִסְקֵי הָאָתוֹן.",
      "source_url": "https://www.sefaria.org/Sforno_on_Numbers_22:23:1"
    },
    {
      "commentator_name": "הטור הארוך",
      "commentary_text": "ותרא האתון את מלאך ה'. כתב הרמב\"ן אי אפשר לומר שראתה המלאך בעיניה כי מלאכי ה' השכלים הנבדלים אינן גוף שיראו לחוש העינים וכאשר יראו לנביאים ישיגו אותם במראות הנפש המשכלת כאשר תגיע למעלת הנבוא' וכ\"ש שלא יראה לעיני בהמה על כן תוכל לפרש ותרא האתון כי הרגישה בדרך דבר מפחיד מלעבור והוא המלאך אשר יצא לשטן כענין ולבי ראה הרבה חכמה ודעת שאומר על המחשבה ולא על הראות. ומה שאומר:",
      "source_url": "https://www.sefaria.org/Tur_HaArokh,_Numbers_22:23:1"
    },
    {
      "commentator_name": "הטור הארוך",
      "commentary_text": "וחרבו שלופה בידו. לא שראתה לא החרב ולא המלאך אלא פי' הפסוק מפני שהיה המלאך נכון להכות בה חרדה חרדה גדולה נראה לה כאילו באין לשחוט אותה ועל כן כאשר אירע הנס ששם לה הבורא הדבור אמרה לבלעם ההסכן הסכנתי לעשות לך כה שלא ידעה למה עשתה עתה כן ולאונסה נעשתה בה כך ולא אמרה לו הנה מלאך עומד לנגדי כי לא עלתה השגתה לדעת זה כלל. ואם נאמר שהמלאכים הנראים בדמות אנוש יושגו אף לעיני הבהמות א\"כ איך לא יראנו בלעם והוא לא הכה בסנורים אלא יתכן שהוסיף בהשגת עיניה מי שהוסיף בה הדבור וראתה כאדם ולא הזכיר הכתוב ויגל ה' את עיני האתון כאשר באדוניה כי הענין כולו באתון נס גדול כבריאה חדשה ואינו נקרא גילוי עינים בלבד. אבל רבותינו לא הזכירו בנסים רך פתיחת הפה. וטעם זה הנס להראות לבלעם מי שם פה לאדם או מי ישום אלם להודיעו כי השם פתח פי הנאלמים וכ\"ש שיאלם כרצונו פי המדברים גם ישים בפיהם לדבר כרצונו להזהירו שלא ילך אחר נחש וקסם ויקללם בהם כי מנחש וקוסם היה:",
      "source_url": "https://www.sefaria.org/Tur_HaArokh,_Numbers_22:23:2"
    },
    {
      "commentator_name": "רבנו בחיי",
      "commentary_text": "ותרא האתון את מלאך ה' נצב בדרך. ראיה זו הרגשה היא איננה ראית עין, כי אין המלאכים מושגים לעיני אדם כל שכן לעיני הבהמות, ואין צריך לומר כי איננה ראית שכל כי הבהמה אין לה שכל, אבל ענין ראיתה שהרגישה בדבר מפחיד אותה ושהיה מעכבה מלעבור ולא ידעה מה הוא, שלא היתה השגתה בכך, שאם כן היה לה לומר בדבורה מלאך ה' עומד לנגדי וחרבו שלופה בידו ועל כן הוצרכתי לעכבך, כך פירש הרמב\"ן ז\"ל.",
      "source_url": "https://www.sefaria.org/Rabbeinu_Bahya,_Bamidbar_22:23:1"
    },
    {
      "commentator_name": "רבנו בחיי",
      "commentary_text": "ותט האתון מן הדרך ותלך בשדה. חפץ גדול היה לאותו רשע לקלל את ישראל, שאין לך אדם בעולם שיראה בדרך הסימנים שראה הוא שלא יחזור, וכל שכן מנחש וקוסם כמוהו שכל אומנותו היתה לקראת נחשים, כי מתחלה נטתה האתון מן הדרך הישר ועקמה כנגד השדה זהו שאמר ותט האתון, שניה ותלחץ אל הקיר ותלחץ את רגל בלעם, רמזה לו בטול פסיעותיו ועכוב הליכתו כי אין רצון הקב\"ה על הכוונה שהיה הולך, שלישית ותרבץ תחת בלעם שרבצה תחתיו ולא רצתה ללכת כלל, וכל אלה רמזים לו כי אותו הדרך לא בחר בו ה', רביעית הנס הגדול שנעשה בדבור האתון, ובכאן פירש לו כי כוונתו רעה בענין הדבור והודיעו מי שם פה לאדם או מי ישום אלם, והנה הש\"י יכול למנוע ממנו הדבור ולשומו בפי הבהמה ועל כן אין לו להתגאות בכח הדבור, חמישית נתפרש לו הדבר יותר כדי לבטל הליכתו על הכוונה שהיה בה ועל כן נגלה אליו מלאך ה' ואמר לו בפירוש הנה אנכי יצאתי לשטן, בעבור כי היה הולך על הכוונה רעה וירט הדרך, כי הקב\"ה אמר לו שילך בדרך על מנת שלא לקלל זהו שאמר קום לך אתם, והוא ירט הדרך כלומר עיות הדרך והולך לנגדי. ואחר כל זה הזכיר שיחזור מן הדרך זהו שאמר לא ידעתי כי אתה נצב לקראתי בדרך ועתה אם רע בעיניך אשובה לי.",
      "source_url": "https://www.sefaria.org/Rabbeinu_Bahya,_Bamidbar_22:23:2"
    },
    {
      "commentator_name": "שפתי חכמים",
      "commentary_text": "רשע זה הניח כלי אומנותו. דקשה לרש\"י דבלא חרב יכול המלאך להמיתו. ועל זה פירש אמר המלאך רשע זה כו', ולכך כתיב שלופה, כלומר שלו פה הפה, לישראל שמתפללים להקב\"ה ולא שלך:",
      "source_url": "https://www.sefaria.org/Siftei_Chakhamim,_Numbers_22:23:1"
    },
    {
      "commentator_name": "אור החיים",
      "commentary_text": "וַתֵּרֶא הָאָתוֹן וְגוֹ׳. צָרִיךְ לָדַעַת כַּוָּנַת ה׳ בְּעִנְיָן זֶה שֶׁנִּתְגַּלָּה הַמַּלְאָךְ לְהָאָתוֹן, גַּם בְּהַעֲמָדַת הַמַּלְאָךְ שָׁלֹשׁ פְּעָמִים בִּשְׁלֹשָׁה מְקוֹמוֹת, וּבִלְחִיצַת רַגְלֵי בִּלְעָם, וּבִרְבִיצָתָהּ, גַּם בִּפְתִיחַת פֶּה הָאָתוֹן, וְכָל מַעֲשֶׂה הָאָמוּר בָּעִנְיָן הוּא עִנְיָן סָתוּם.",
      "source_url": "https://www.sefaria.org/Or_HaChaim_on_Numbers_22:23:1"
    },
    {
      "commentator_name": "אור החיים",
      "commentary_text": "וְנִרְאֶה כִּי כָּל כַּוָּנַת ה׳ בְּעִנְיָן זֶה לֹא הָיְתָה אֶלָּא לְהַשְׁפִּיל גַּאֲוָתוֹ שֶׁל בָּזוּי זֶה, לְפִי שֶׁקָּדַם וְנָהַג גַּבְהוּת לִפְנֵי ה׳ כְּמוֹ שֶׁכָּתַבְנוּ לְמַעְלָה שֶׁלֹּא אָמַר לַשָּׂרִים כִּי הוּא הוֹלֵךְ בִּרְשׁוּת ה׳ אֶלָּא כְּאָדָם הָעוֹמֵד בִּרְשׁוּת עַצְמוֹ, לָזֶה בִּקֵּשׁ לוֹ ה׳ הַשְׁפָּלָה שֶׁאֵין לְמַטָּה מִמֶּנָּה וְשָׂחַק בּוֹ בְּקָלוֹן מְכֹעָר וּמְשֻׁנֶּה. וְדָבָר יָדוּעַ הוּא כִּי הַהַרְכָּבָה הַחִיּוּנִית אֲשֶׁר הִרְכִּיב ה׳ בְּבַעֲלֵי חַיִּים בִּלְתִּי מְדַבְּרִים הִיא מְשֻׁנָּה מֵהַרְכָּבָה הַחִיּוּנִית שֶׁפָּעַל ה׳ וְעָשָׂה בְּבַעֲלֵי חַיִּים הַמְּדַבְּרִים, וְלָזֶה כְּשֶׁרָצָה ה׳ שֶׁתִּפְתַּח הָאָתוֹן אֶת פִּיהָ לְדַבֵּר כְּבַעֲלֵי חַיִּים הַמְּדַבְּרִים הֻצְרַךְ לְהַרְכִּיב בָּהּ הַרְכָּבָה הַחִיּוּנִית שֶׁל בַּעֲלֵי חַיִּים הַמְּדַבְּרִים, וְהוּא מַה שֶׁפָּעַל ה׳ בְּמַעֲשֵׂה הַעֲמָדַת הַמַּלְאָךְ בִּשְׁלֹשָׁה מְקוֹמוֹת וּבִרְאִיַּת הָאָתוֹן הַמַּלְאָךְ שָׁלֹשׁ פְּעָמִים, כִּי כֹּחַ הַמְּדַבֵּר צָרִיךְ שָׁלֹשׁ הֲכָנוֹת קוֹדְמוֹת לוֹ, וְהֵם כֹּחַ הַצּוֹמֵחַ שֶׁהוּא בְּכָל הַנִּבְרָאִים, וְכֹחַ הַמֵּנִיעַ, וְאַחַר כָּךְ כֹּחַ הַמְּדַבֵּר. לָזֶה עָמַד פַּעַם רִאשׁוֹנָה וְרָאֲתָה הָאָתוֹן אוֹתוֹ וּפָעַל בָּהּ בְּכֹחַ רְאוּת הָרוּחָנִי כֹּחַ אֶחָד מִמִּין הַרְכָּבַת כֹּחַ הַצּוֹמֵחַ שֶׁבּוֹ יִתְקַבֵּל כֹּחַ הַמְּדַבֵּר, וְעָמַד פַּעַם שְׁנִיָּה וְרָאֲתָה אוֹתוֹ וּפָעַל בָּהּ כֹּחַ הַמֵּנִיעַ הַמִּתְקַבֵּל בּוֹ כֹּחַ הַמְּדַבֵּר, וּבְפַעַם שְׁלִישִׁית פָּעַל בָּהּ כֹּחַ הַמְּדַבֵּר, וְאָז פָּתַח ה׳ אֶת פִּיהָ וְדִבְּרָה דִּבְרֵי הֲבָנָה בְּדֶרֶךְ שׁוֹאֵל וּמֵשִׁיב, וְהִכְלִימָה אֶת בִּלְעָם בְּדֶרֶךְ בִּזּוּי בִּפְנֵי נְעָרָיו וְכוּ׳, וּבִזּוּי שֶׁיִּהְיֶה בְּדֶרֶךְ זֶה יֵשׁ לוֹ קוֹל, לִהְיוֹתוֹ דָּבָר תָּמוּהַּ בִּשְׁנֵי אוֹפָנִים, אֹפֶן אֶחָד שֶׁתְּדַבֵּר הַבְּהֵמָה, וְהַשֵּׁנִי שֶׁאָדָם גָּדוֹל כְּבִלְעָם הָיְתָה לוֹ אֲתוֹנוֹ לְאִשָּׁה שׁוֹכֶבֶת חֵיקוֹ.",
      "source_url": "https://www.sefaria.org/Or_HaChaim_on_Numbers_22:23:2"
    },
    {
      "commentator_name": "אור החיים",
      "commentary_text": "וְנִשְׁאַר לָדַעַת לָמָּה עָמַד הַמַּלְאָךְ בִּשְׁלֹשָׁה מְקוֹמוֹת שׁוֹנוֹת, וְיָכוֹל הָיָה לְהִתְרָאוֹת לָהּ שָׁלֹשׁ  פְּעָמִים בְּמָקוֹם אֶחָד. וְאוּלַי כִּי עָשָׂה לוֹ כְּנֶגֶד שְׁלֹשָׁה דְּבָרִים שֶׁעָשָׂה בְּרִשְׁעוֹ: א׳ שֶׁהַשֵּׁם אָמַר אֵלָיו פַּעַם אַחַת לֹא תֵלֵךְ לֹא תָאוֹר, וְהוּא לֹא אָמַר לַשָּׂרִים מַאֲמַר ״לֹא תָאוֹר״ וְגוֹ׳, שֶׁזֶּה הָיָה סִבָּה לִשְׁלֹחַ אֲחֵרִים, וּכְנֶגֶד זֶה נִצָּב פַּעַם אַחַת בַּדֶּרֶךְ וְנָטְתָה הָאָתוֹן מֵהַדֶּרֶךְ, כְּשֵׁם שֶׁהוּא נָטָה מֵהַדֶּרֶךְ אֲשֶׁר אָמַר ה׳ אֵלָיו כַּנִּזְכָּר. ב׳ שֶׁהַשֵּׁם אָמַר אֵלָיו אִם לִקְרֹא לְךָ וְגוֹ׳, שֶׁתְּנַאי הוּא הַדָּבָר עַד שֶׁיֵּדַע בְּוַדַּאי שֶׁיֵּשׁ לוֹ הֲנָאָה בַּדָּבָר, וּבָזֶה רְמָזוֹ שֶׁאֵין לוֹ הֲנָאָה וְלֹא הִרְגִּישׁ. וּכְנֶגֶד זֶה עָמַד הַמַּלְאָךְ בְּמִשְׁעוֹל הַכְּרָמִים וַתִּלְחַץ הָאָתוֹן רַגְלָיו, לֵאמֹר שֶׁלְּחָצוֹ ה׳ בְּנֹעַם דְּבָרָיו לְהַשְׂכִּיל לְהֵיטִיב לְבַל יֵלֵךְ. הַג׳ שֶׁהַשֵּׁם אָמַר אֵלָיו בְּעֵת רִשְׁיוֹן הַהֲלִיכָה אַךְ אֶת הַדָּבָר וְגוֹ׳, וְדִבּוּר זֶה הוּא מְדֻיָּק, אֵין לִנְטוֹת בְּמַשְׁמָעוּתוֹ אָנָה וָאָנָה, וְהוּא הָרָשָׁע הָלַךְ בְּעֵצָה אַחֶרֶת כְּמוֹ שֶׁדִּיַּקְנוּ מִמַּאֲמַר ״הוֹלֵךְ הוּא״ גַּם מֵאָמְרוֹ ״וְהוּא רוֹכֵב״ וְגוֹ׳ ״וּשְׁנֵי נְעָרָיו״ וְגוֹ׳, וְהוּא מַה שֶׁעָמַד הַמַּלְאָךְ בְּמָקוֹם צָר אֲשֶׁר אֵין דֶּרֶךְ וְגוֹ׳, וְרָבְצָה הָאָתוֹן תַּחְתָּיו, שֶׁזֶּה יִרְמֹז לוֹמַר שֶׁאֵין ה׳ חָפֵץ בַּדָּבָר שֶׁהוּא חָפֵץ לָלֶכֶת עָלָיו.",
      "source_url": "https://www.sefaria.org/Or_HaChaim_on_Numbers_22:23:3"
    },
    {
      "commentator_name": "רקנאטי על התורה",
      "commentary_text": "ותרא האתון את מלאך יי' נצב בדרך וחרבו שלופה בידו וגומר. בעבור כי ראיית המלאכים מן העטרה על כן וחרבו שלופה בידו. וכתב הרב הגדול ז\"ל מלאכי השם השכלים הנבדלים לא יראו לחוש העינים כי אינו גוף נתפש במראה וכאשר יראו לנביאים או לאנשי רוח הקדש כדניאל ישיגו אותן במראות הנפש המשכלת כאשר תגיע למעלת הנבואה או למדרגה שתחתיה אבל שיושגו לעיני בהמה אי אפשר על כן תוכל לפרש ותרא האתון כי הרגישה בדבר מפחיד אותה לעבור והוא המלאך אשר יצא לשטן לו כענין ולבי ראה הרבה חכמה ודעת (קהלת א טז) שיאמר על ההשגה לא על הראות וכאשר אירע לה הנס ושם לה השם יתברך הדבור אמרה לבלעם ההסכן הסכנתי לעשות לך כה אבל לא ידעה למה עשתה כן כי לאונסה נעשה בה כך ולפיכך לא אמרה לו הנה מלאך השם עומד לנגדי כי לא עלתה השגתה לדעת זה כלל ואם נאמר כי המלאכים הנראים בדמות אנושי כאשר הזכרתי בפרשת וירא יושגו אף לעיני הבהמות אם כן איך לא יראנו בלעם ולא הוכה בסנוירים אלא יתכן שהוסיף בהשגת עיניה מי שהוסיף בה השגת הדבור וראתה כאדם. ולא הזכיר בה הכתוב ויגל י\"י את עיני האתון כאשר הזכיר באדוניה כי הענין כולו באתון נס גדול כבריאה חדשה בנבראים בין השמשות אינו נקרא גלוי עינים לבד אבל רבותינו ז\"ל לא יזכירו בנסים רק פתיחת פיה. וטעם הנס הזה להראות לבלעם מי שם פה לאדם או מי ישום אלם להודיע כי השם יתברך פותח פי הנאלמים וכל שכן שיאלם כרצונו פי המדברים כי הכל בידו ולהזהירו שלא ילך אחרי נחש וקסם ויקללם בהם כי מנחש היה וקוסם עד כאן לשון הרב ז\"ל. ואנו לא נוכל להכחיש דברים הנוראים הנראים לעין תמיד וגם רבותינו ז\"ל אמרו מלאך המות בא לעיר כלבים צועקים. וטעם שבעת המזבחות כתב הרב הנזכר כי בלעם רצה לדבק אליו רצון מאת השם בקרבנות האלו ולכך העלה עולות מספר כולם ורצה שיתעסק בלק עצמו בהם ולכך אמר ויעל בלק ובלעם פר ואיל במזבח זה שוחט וזה זורק עד כאן לשון הרב ז\"ל. וזה טעם המזבחות בה\"א הידיעה ותמצא כי האבות כלן לא הקריבו רק ז' מזבחות וזה הרשע מגודל רשעו ותאותו לקלל את ישראל נתכון להסכים לצייורו ומחשבתו כל הכחות כדי שיתקיים חפצו במה שירצה לעשות. וטעם ויקר כמו ויקרא וכבר פירשנו טעם חצי הדבור ונכתב בחסרון האל\"ף כי לא תמצא ענינם בשלימות כי אם בחסרון. וכן יחזקאל הנביא ע\"ה בראותו רוח סערה אמר וארא ולא אמר ואראה כי כל נביאים שהבינו בסבה ההיא לא נאמר שראו ראייתם תשלום אלא בגירעון וזהו סוד ויוקים ואנשי כוזבא ויואש ושרף אשר בעלו למואב (ד\"ה א' ד כב) ונתפרש הפסוק הזה כתעלומות חכמה לכחות הטומאה המתפשטין בעולם:",
      "source_url": "https://www.sefaria.org/Recanati_on_the_Torah,_Balak_5"
    },
    {
      "commentator_name": "ביאור שטיינזלץ",
      "commentary_text": "וַתֵּרֶא הָאָתוֹן אֶת מַלְאַךְ ה' נִצָּב, עומד בַּדֶּרֶךְ, וְחַרְבּוֹ שְׁלוּפָה בְּיָדוֹ. לא ברור מה ראתה וידעה האתון, אך בוודאי חשה באיום של ממש, וַתֵּט, נטתה הָאָתוֹן מִן הַדֶּרֶךְ, וַתֵּלֶךְ בַּשָּׂדֶה. וַיַּךְ בִּלְעָם אֶת הָאָתוֹן לְהַטֹּתָהּ שוב אל הַדָּרֶךְ.",
      "source_url": "https://www.sefaria.org/Steinsaltz_on_Numbers_22:23"
    },
    {
      "commentator_name": "שפתי כהן",
      "commentary_text": "ותרא האתון את מלאך ה'. פירש הרמב\"ן ז\"ל, ראיה זו אינה ראיה ממש אלא הרגישה בעצמה דבר המפחיד אותה ומעכבה, כי אין המלאכים נראים לבני אדם כ\"ש לבהמות, והראיה שלא אמרה בדבורה מלאך ה' לנגדי וחרבו שלופה בידו ועל כן הוכרחתי לעכבך. עוד יכולין לומר שראתה ראיה ממש, ולהראותו שהיא רואה והוא אינו רואה, שהוא פחות מן הבהמה, וכן אמר המלאך ותראני האתון ותט לפני זה שלש רגלים. וכן פירש\"י ז\"ל, ותרא האתון והוא לא ראה, שהקב\"ה נתן רשות לבהמה לראות יותר מן האדם, שמתוך שיש בו דעת תטרף דעתו כשיראה, ע\"כ:",
      "source_url": "https://www.sefaria.org/Siftei_Kohen_on_Torah,_Numbers_22:23:1"
    },
    {
      "commentator_name": "שפתי כהן",
      "commentary_text": "ותט האתון מן הדרך. בראיית המלאך פשטה כל מה שעליה מתיקונוי דאתקין בחרשוי ובקסמוי. וכן אמר בזוהר, ותט האתון מן הדרך, סאטת מן ההוא אורחא דהות טעינא מסטרא דדינא קשיא לקבליהון דישראל, ובמא חמא בלעם דהיא סאטת מן ההיא אורחא, אלא הכי אמר ר' שמעון אפילו באורחא בעא לאבאשא לישראל בחילא דאתניה, וכיון דלא סליק בידוי מה כתיב ויך את האתון במקל, אטען לה ואלבש לה בזריזו דדינא קשיא תקיפא, הה\"ד במקל, במקל דייקא, דאיהו דינא קשיא תקיפא, במקלו לא כתיב אלא במקל פוק חמי כמה חכמתא תקיפא דההוא רשיעא ותיאובתא דיליה לאבאשא לישראל, דאיהו אשגח לנפקא מרשותיה דלעילא בגין דתיאובתיה לאתיקרא ולאבאשא לישראל:",
      "source_url": "https://www.sefaria.org/Siftei_Kohen_on_Torah,_Numbers_22:23:2"
    },
    {
      "commentator_name": "אבן עזרא",
      "commentary_text": "מן הדרך. הדרוך והלכה בשדה שאין שם דרך:",
      "source_url": "https://www.sefaria.org/Ibn_Ezra_on_Numbers_22:23:1"
    },
    {
      "commentator_name": "אבן עזרא",
      "commentary_text": "להטותה הדרך. דרך קצרה והטעם אל הדרך:",
      "source_url": "https://www.sefaria.org/Ibn_Ezra_on_Numbers_22:23:2"
    },
    {
      "commentator_name": "כלי יקר",
      "commentary_text": "וַתֵּט הָאָתוֹן מִן הַדֶּרֶךְ וְגוֹ׳. בַּתַּנְחוּמָא (בלק ח) אָמְרוּ: סִימָנֵי אָבוֹת הֶרְאָה לוֹ כוּ׳. כִּי ״וַתֵּלֶךְ בַּשָּׂדֶה״ מָקוֹם רָחָב, לוֹמַר שֶׁאִם יִרְצֶה לְקַבֵּל זֶרַע אַבְרָהָם יִמְצָא לְקַלֵּל בְּנֵי קְטוּרָה, וְיִשְׁמָעֵאל. וְאִם יִרְצֶה לְקַלֵּל זֶרַע יִצְחָק, יִמְצָא צַד אֶחָד לְקַלֵּל, כִּי יָכוֹל לְהַטּוֹת אֶל עֵשָׂו. אַךְ מִצַּד יַעֲקֹב, שֶׁהָיְתָה מִטָּתוֹ שְׁלֵמָה, עָמַד בְּמָקוֹם צָר, כִּי מִצִּדּוֹ ״אֵין דֶּרֶךְ לִנְטוֹת יָמִין וּשְׂמֹאל״. וְיֵשׁ עוֹד דְּרָכִים אֲחֵרִים אֶל הַמְפָרְשִׁים.",
      "source_url": "https://www.sefaria.org/Kli_Yakar_on_Numbers_22:23:1"
    },
    {
      "commentator_name": "כלי יקר",
      "commentary_text": "וּמִדְּכָתַב רַשִׁ״י ״זֶה שָׁלֹשׁ רְגָלִים״, אַתָּה רוֹצֶה לַעֲקוֹר אֻמָּה הַחוֹגֶגֶת שָׁלֹשׁ רְגָלִים (במד״ר כ יד), שְׁמַע מִנַּהּ שֶׁאוֹתָן שְׁלֹשָׁה סִימָנִים שֶׁהִזְכִּיר הֵם כְּנֶגֶד שָׁלֹשׁ רְגָלִים, וּמַתְחִיל מִן סֻכּוֹת אֲשֶׁר בְּחֹדֶשׁ תִּשְׁרֵי, רֹאשׁ הַשָּׁנָה, שֶׁנֶּאֱמַר בּוֹ (דברים טז יג): ״בְּאָסְפְּךָ מַעֲשֶׂיךָ מִן הַשָּׂדֶה״, וְעָלָיו נֶאֱמַר: ״וַתֵּט הָאָתוֹן מִן הַדֶּרֶךְ וַתֵּלֶךְ בַּשָּׂדֶה״, אַתָּה רוֹצֶה לַעֲקוֹר אֻמָּה הַחוֹגֶגֶת חַג הָאָסִיף הַתָּלוּי בַּשָּׂדֶה, וּבוֹ מַקְרִיבִים יִשְׂרָאֵל שִׁבְעִים פָּרִים כְּנֶגֶד שִׁבְעִים אֻמּוֹת, וְאִם כֵּן בִּטּוּלָם גּוֹרֵם בִּטּוּל כָּל הָאֻמּוֹת.",
      "source_url": "https://www.sefaria.org/Kli_Yakar_on_Numbers_22:23:2"
    },
    {
      "commentator_name": "כלי יקר",
      "commentary_text": "וְאַחַר כָּךְ אָמַר ״בְּמִשְׁעוֹל הַכְּרָמִים״, רֶמֶז לְחַג הַפֶּסַח, זְמַן יְצִיאַת מִצְרַיִם, שֶׁנֶּאֱמַר (תהלים פט): ״גֶּפֶן מִמִּצְרַיִם תַּסִּיעַ תְּגָרֵשׁ גּוֹיִם וַתִּטָּעֶהָ״, כִּי הַדִּין נוֹתֵן לַעֲקוֹר הַקּוֹצִים וְלִטַּע הַגֶּפֶן, וְאֵיךְ אַתָּה רוֹצֶה לְהַחֲלִיף הַקְּעָרָה וְלַעֲקוֹר הַכְּרָמִים מִפְּנֵי הַקּוֹצִים? וְדֶרֶךְ הַגֶּפֶן שֶׁהוּא נִרְפָּס בָּרַגְלַיִם וּלְסוֹף הַיַּיִן מַפִּיל אֶת זֶה הָרוֹפְסוֹ כְּשֶׁשּׁוֹתֵהוּ, כִּדְמַסִּיק בַּיַּלְקוּט פָּרָשַׁת וַיֵּשֶׁב (קמו.) בְּשֵׁם מִדְרָשׁ שׁוֹחֵר טוֹב, וְשָׁם מֵבִיא הַרְבֵּה דִּמְיוֹנוֹת עַל שֶׁיִּשְׂרָאֵל נִמְשְׁלוּ לְגֶפֶן, וְכֻלָּם שַׁיָּכִים לְבַטֵּל דַּעַת בִּלְעָם. וְרֶמֶז לְחַג הַפֶּסַח שֶׁבּוֹ שׁוֹתִים אַרְבַּע כּוֹסוֹת שֶׁל יַיִן כְּנֶגֶד כּוֹס יְשׁוּעוֹת לְיִשְׂרָאֵל שֶׁנִּמְשְׁלוּ לְגֶפֶן, וּכְתִיב אַרְבַּע לְשׁוֹנוֹת שֶׁל גְּאֻלָּה, וּכְנֶגְדָּם הַקָּדוֹשׁ בָּרוּךְ הוּא מַשְׁקֶה לָאֻמּוֹת אַרְבַּע כּוֹסוֹת תַּרְעֵלָה, כִּדְמַסִּיק בְּבֵרֵאשִׁית רַבָּה (וישב פח ה), וְאֵיךְ אַתָּה רוֹצֶה לַעֲקוֹר כָּל זֶה וּלְהַחֲלִיף הַשִּׁיטָה בֵּין יִשְׂרָאֵל לָעַמִּים?",
      "source_url": "https://www.sefaria.org/Kli_Yakar_on_Numbers_22:23:3"
    },
    {
      "commentator_name": "כלי יקר",
      "commentary_text": "וְאַחַר כָּךְ אָמַר ״וַיַּעֲמֹד בְּמָקוֹם צָר אֲשֶׁר אֵין דֶּרֶךְ לִנְטוֹת יָמִין וּשְׂמֹאל״, כְּנֶגֶד עֲצֶרֶת שֶׁבּוֹ קִבְּלוּ אֶת הַתּוֹרָה, שֶׁנֶּאֱמַר בָּהּ (משלי ג טז): ״אֹרֶךְ יָמִים בִּימִינָהּ בִּשְׂמֹאלָהּ עֹשֶׁר וְכָבוֹד״, וְאִלְמָלֵא קִבְּלוּ יִשְׂרָאֵל הַתּוֹרָה הָיָה הָעוֹלָם חוֹזֵר לְתֹהוּ וָבֹהוּ (שבת פח.) וְהָיוּ כָּל הָאֻמּוֹת בְּטֵלִין, וְאֵיךְ אַתָּה רוֹצֶה לַעֲקוֹר אוּמָּה זוֹ הַחוֹגֶגֶת חַג זֶה שֶׁיֵּשׁ בּוֹ צֹרֶךְ לְכָל הָאֻמּוֹת וּלְכָל הַנִּמְצָאִים שֶׁבְּמַעְלָה וְשֶׁבְּמַטָּה? וְיָכוֹל לִהְיוֹת שֶׁגַּם ״בְּמִשְׁעוֹל הַכְּרָמִים״ רָמַז לוֹ אַתָּה רוֹצֶה לַעֲקוֹר אֻמָּה הַחוֹגֶגֶת חַג הַפֶּסַח וְשׁוֹתִין בּוֹ אַרְבַּע כּוֹסוֹת, כְּנֶגֶד אַרְבַּע מַלְכֻיּוֹת, וְשֶׁל יַיִן כְּמִסְפַּר שִׁבְעִים כְּנֶגֶד שִׁבְעִים אֻמּוֹת, וּבִטּוּל זֶה גּוֹרֵם גַּם כֵּן בִּטּוּל כָּל שִׁבְעִים אֻמּוֹת.",
      "source_url": "https://www.sefaria.org/Kli_Yakar_on_Numbers_22:23:4"
    },
    {
      "commentator_name": "כלי יקר",
      "commentary_text": "וְיִתָּכֵן עוֹד לְפָרֵשׁ זֶה שָׁלֹשׁ רְגָלִים, שֶׁרָמַז לוֹ, אֵיךְ אַתָּה רוֹצֶה לַעֲקוֹר אֻמָּה הַמַּחֲזֶקֶת בִּשְׁלֹשָׁה דְּבָרִים אֲשֶׁר עֲלֵיהֶם הָעוֹלָם עוֹמֵד (אבות א ב), דְּהַיְנוּ שָׁלֹשׁ רַגְלֵי הָעוֹלָם וְהֵם: הַתּוֹרָה, עֲבוֹדָה, גְּמִילוּת חֲסָדִים, כִּי בִּטּוּלָם הֶרֶס כָּל הָעוֹלָם. וְרָמַז לוֹ גְּמִילוּת חֲסָדִים בְּמַה שֶּׁאָמַר ״וַתֵּלֶךְ בַּשָּׂדֶה״, כִּי עִקַּר הַגְּמִילוּת חֲסָדִים מִן הַשָּׂדֶה עַל יְדֵי תְּרוּמוֹת וּמַעַשְׂרוֹת וְלֶקֶט שִׁכְחָה פֵּאָה. וְהָעֲבוֹדָה שֶׁבְּבֵית הַמִּקְדָּשׁ שֶׁנִּמְשַׁל לְכֶרֶם רָמַז לוֹ ״בְּמִשְׁעוֹל הַכְּרָמִים״, וְכֵן פֵּרֵשׁ רַשִׁ״י ״הֱבִיאַנִי אֶל בֵּית הַיָּיִן״ (שיר ב ד), זֶה אֹהֶל מוֹעֵד, וַעֲלֵיהֶם נֶאֱמַר (שם ז יב-יג): ״לְכָה דוֹדִי נֵצֵא הַשָּׂדֶה, נַשְׁכִּימָה לַכְּרָמִים״ וְגוֹ׳. וּ״בְמָקוֹם צָר אֲשֶׁר אֵין דֶּרֶךְ לִנְטוֹת יָמִין וּשְׂמֹאל״ רָמַז לַתּוֹרָה בְּדֶרֶךְ שֶׁנִּתְבָּאֵר, וְזֶה רֶמֶז נָכוֹן.",
      "source_url": "https://www.sefaria.org/Kli_Yakar_on_Numbers_22:23:5"
    },
    {
      "commentator_name": "קיצור בעל הטורים ",
      "commentary_text": "ותט שלשה במס' בהאי ענינא תרי וחד ותט אשורנו מני ארחך למה ותט האתון בשביל ותט אשורנו שבלעם נטה מני ארחך שהיה חפץ לקללם והקב\"ה רצה לברכם:",
      "source_url": "https://www.sefaria.org/Kitzur_Ba'al_HaTurim_on_Numbers_22:23:1"
    },
    {
      "commentator_name": "דעת זקנים",
      "commentary_text": "ותלך בשדה וגו'. פירש\"י סימני אבות הראהו וצריך פי' לפי' וה\"ק בתחלה עמד בשדה נגדו שיש דרך לנטות ימין ושמאל רמז לו שאם ירצה לקלל זרעו של אברהם יקלל מימין ומשמאל. בני ישמעאל מצד אחד ובני קטורה מצד אחד אבל לא תלך באמצע אל תקלל זרע יצחק ואחר עמד במשעול הכרמים שאין דרך שם כי אם דרך הלוך שני אנשי' בצמצום ורמז לו שאם בא לקלל זרעו של יצחק שיוכל לקלל' מצד אחד דהיינו מצדו של עשו אבל לא מצד השני מצד יעקב. ואחר עמד במקום צר אשר אין דרך לנטות ימין ושמאל כי כל בניו כשרים הם דהיינו זרע יעקב זהו סימני האבות הראהו:",
      "source_url": "https://www.sefaria.org/Da'at_Zekenim_on_Numbers_22:23:1"
    },
    {
      "commentator_name": "העמק דבר",
      "commentary_text": "ותרא האתון. ולא כתיב ויגל ה׳ את עיני האתון. ומה שפרש״י שנתן הקב״ה רשות לבהמה לראות כו׳ כשיראה מזיקין עכ״ל. אינו ענין למלאכים שכלים הנבדלים בקדושה. ותו למאי התראה לה עם חרבו שלופה בידו. הן מה שהתראה לבלעם כך. הוא ניתן ללמדו בינה כמבואר בפרש״י בשם המדרש. אבל להאתון הי׳ די להפחידה במראה איומה אלא נראה שלא התראה לה במראה מלאך ה׳ כי אם במראה אדם וחרבו שלופה בידו. ונפחדה כטבע הבהמה לפני האדם. וגם מפני החרב. אמנם גם זה הי׳ שלא בטבע לראות שהרי לא ראה בלעם וכקושית הרמב״ן ז״ל. אלא הי׳ ראי׳ נפלאה שיהא מלאך נראה בדמות איש. ומכ״מ ניחא הא דלא כתיב ויגל ה׳ את עיני האתון היינו כדי שלא יהי׳ מוכח שהאתון הבינה שהוא מלאך ה׳. מש״ה לא כתיב כלל. דאע״ג שראתה מכ״מ לא ידעה מאומה ולא נגלו עיניה. ואולי לזה כוון רש״י דלפרקים בהמה רואה מזיקין היינו שדים. ונדמה לה באותו פנים. ובלעם לא ראה גם זה:",
      "source_url": "https://www.sefaria.org/Haamek_Davar_on_Numbers_22:23:1"
    },
    {
      "commentator_name": "העמק דבר",
      "commentary_text": "להטתה הדרך. מדלא כתיב במקל כמו להלן בשלישית. מובן שהכה אותה בידו. ופירש הכתוב שלא הכה אותה כדי שתרגיש כאב. אלא הכתה בידו להטתה הדרך. וכן הי׳ שבהכאה זו הטה אותה לצד הדרך:",
      "source_url": "https://www.sefaria.org/Haamek_Davar_on_Numbers_22:23:2"
    },
    {
      "commentator_name": "בכור שור",
      "commentary_text": "ותלך בשדה. בתחילה נראה לה המלאך במקום רחב ידים ונטתה בשדה מפני המלאך ואחר כך, בין גדרי הכרמים, לא יכלה לנוס ודחקה עצמה אצל הגדר ולחצה את רגלו ואחר כך במקום צר כגון שהיה אם הדרך גבוה ועומק גדול מכאן ומכאן שאם תטה לכאן ולכאן היתה נופלת ותמות היא והוא ולכך רבצה תחתיו ולכך חרה אפו כי [אמר עתה שהזקתי ברגלי איני יכול לילך ברגל רבצה תחתי] ואינה רוצה לישא אותי:",
      "source_url": "https://www.sefaria.org/Bekhor_Shor,_Numbers_22:23:1"
    },
    {
      "commentator_name": "חזקוני",
      "commentary_text": "וחרבו שלופה בידו מדה כנגד מדה שאמר לו יש חרב בידי.",
      "source_url": "https://www.sefaria.org/Chizkuni,_Numbers_22:23:1"
    },
    {
      "commentator_name": "מזרחי",
      "commentary_text": "וחרבו שלופה בידו אמר רשע זה הניח כלי אומנתו שכלי זיינן של אומות העולם בחרב והוא בא עליהם בפיו וכו'. במדבר רבה דאם לא כן למה חרבו שלופה בידו וכי לא היה לו למלאך לנשוף אותו בפיו ויוצא כל רוחו כמו בסנחריב שכתוב בו ויצא מלאך יי' ויך במחנה אשור וגם נשף בהם וייבשו וכו' כדאי' במדבר רבה:",
      "source_url": "https://www.sefaria.org/Mizrachi,_Numbers_22:23:1"
    },
    {
      "commentator_name": "אדרת אליהו",
      "commentary_text": "מהדורא תליתאהותרא האתון את מלאך ה' נצב בדרך. ואח״כ ויעמד במשעול הכרמים גדר מזה וגדר מזה. ואח״כ ויעמד במקום צר אשר אין דרך לנטות ימין ושמאול. הענין הוא כי הראה לו ג״ד שהם מגינים על ישראל ולכך לא יוכל לעשות להם מאומה וכמ״ש כי נר מצוה. ותורה אור. ודרך חיים תוכחות מוסר. והם ג' מצוה. ותורה. ויראה. והראהו המלאך ג' דברים אלו מלמעלה למטה בתחילה נצב בדרך. הוא דרך חיים דכתיב ביה דרך ואח״כ במשעול הכרמים הוא התורה גדר מזה וגדר מזה דבתורה כתיב בה מזה ומזה הם כתובים תורה שבכתב ותורה שבע״פ ולכך כתיב שני פעמים זה והוא כ״ד נגד כ״ד ספרים. ומצינו כמה פעמים שהתורה נמשלה לכרם בכרם ביבנה כרמי שלי. ואח״כ ויעמד במקום צר אשר אין דרך לנטות ימין ושמאול. הן המצות שאין דרך לנטות מהם ימין ושמאל וכמ״ש לא תוסף ולא תגרע וכמ״ש אלה המצות שאין נביא רשאי לחדש דבר אבל בתורה יכול להוסיף חידושים וסייגים ובמצות אסור להוסיף או למעט וכמ״ש אל תט ימין ושמאל הסר רגלך מרע ולכך כתיב כאן אשר אין דרך לנטות ימין ושמאול ועוד אמרו רז״ל סימני אבות הראה לו וכנגדן ג' רגלים פסח נגד אברהם שאפה מצות שבועות נגד יצחק שכתוב בו שקרא לבאר שבעה ובשבועו' כתיב שבעה שבועות תספ' לך וסוכות נגד יעקב וכמ״ש ויעקב נסע סכתה ולכך נקראו רגלים שצריך לעלות ברגלים לראות המקדש וכמו שהאבות כל א' וא' כלול מג' כמ״ש בכל מכל כל. כן כלולין השלש רגלים כל א' משלשתן וג״כ נכתבו ג״פ בתורה בג' בריתות א' בפ' משפטים בברית לוחות הראשונים וא' בפ' כי תשא בברית לוחות שניות וא' בברית של ערבות מואב וכנגד כן כתיב כאן תיבות שלש רגלים ג״כ ג״פ א' בדברי האתון לבלעם ושני פעמים בדברי המלאך וכמו שהרגלים נאמרו ב״פ מפי הגבורה דהיינו במשפטים ובכי תשא והג' ע״י משה. כן כאן ב״פ אמר המלאך ג' רגלים ופעם השלישי אמרה האתון וז״ש סימני אבות וזכות רגלים הראה לו:",
      "source_url": "https://www.sefaria.org/Aderet_Eliyahu,_Numbers_22:23:1"
    },
    {
      "commentator_name": "אדרת אליהו",
      "commentary_text": "וחרבו שלופה בידו. הענין מה שכתוב וחרבו. הוא כמ״ש כי זבח גדול לה' בבצרה וטבח גדול בארץ אדום א' לתתא וא' לעינא ולכך גם כאן כתיב ב״פ וחרבו שלופה בידו א' בפסוק ותרא האתון וגו' וחרבו שלופה וא' בפסוק ויגל ה' את עיני בלעם וגו' וחרבו שלופה בידו וכך היה שבאותו פעם תיכף הרג את האתון בחרב ובפעם השניי' נהרג בלעם וכמ״ש בפ' מטות נקם את נקמת כו' ויצבאו על מדין ויהרגו כל זכר כו' ולא הזכיר כלל חרב ואח״כ כתיב ואת בלעם בן בעור הרגו בחרב דייקא בחרב הידוע והמיוחד לו וזהו החרב השני שנכתב כאן שני פעמים וחרבו שלופה חד לעילא וחד לתתא וכמ״ש כי זבח גדול ג״כ שני מיני חרב כדלעיל ולכן אמר המלאך לבלעם כי עתה גם אתכה הרגתי תיבת עתה דייקא שודאי סופו ליהרג בחרב ההוא אלא שגם עתה הרגתי ולא הייתי ממתין עד עת ההיא:",
      "source_url": "https://www.sefaria.org/Aderet_Eliyahu,_Numbers_22:23:2"
    },
    {
      "commentator_name": "מלבי\"ם",
      "commentary_text": "ותט האתון מן הדרך מה שעכב את האתון ג' פעמים דוקא היה בזה משל מתיחס לענין בלעם, שטבע אתון זו ומנהגה היה שתהיה מונהגת מהרוכב עליה ושלא תמרה בו, ועתה בטלה טבע זו ג' פעמים בג' מדרגות, בפעם הא' רכב עדיין עליה רק שלא הלכה אל הצד שהוא מכוין אליו, ובפעם הב' הוסיפה להזיק את הרוכב וללחצו אל הקיר, ובפעם הג' רבצה תחתיו עד שלא יכול לרכב עליה כלל, וזה תוכחה אל בלעם שגופו החמרי הוא האתון שלו, ויצרו הרע הוא הרוכב על חמרו ומנהיגו תמיד כפי רצונו, ועתה בטל חמרו בפעם הא' עצת רוכבו, ר\"ל עצת היצה\"ר שלו, מפני ה' ומלאכיו, במה שלא הלך בעצת יצרו לאור אותם, רק רצה ללכת לקוב לבד שהוא נטיה מדרכו, ובפעם הב' הוסיף לבטל רצון רוכבו במה שרצה ללכת כפי רצון ה' אף שיצטרך לברכם שבזה ילחץ רגל הרוכב, כי תחת שימלא רצון יצרו להשיג מתנות וכבוד ישיג בוז וקלון, והראו לו כי אתונו הוסיפה להכנע מפני מלאך ה' בפעם השלישית יותר ממנו כי רבצה תחת בלעם וחדלה מלכת וכן הי' ראוי שהוא יחדל מלכת לגמרי:",
      "source_url": "https://www.sefaria.org/Malbim_on_Numbers_22:23:1"
    },
    {
      "commentator_name": "ברכת אשר על התורה",
      "commentary_text": "רש\"י ד\"ה ותרא האתון, ...שמתוך שיש בו דעת, תטרף דעתו כשיראה מזיקין. ע\"כ. כלומר אין לבהמה מעלה יתירה על האדם, אלא שהאדם, מתוך שיש בו דעת, עלולה דעתו להטרף משיראה מלאכים רעים (\"מזיקין\"), לכן הסתיר ה' מעיניו את הדברים הרוחניים, ולעומתו גילה את עיני הבהמה, שאין בה דעת להתיירא מהמלאכים הרעים, ומתוך כך ראתה גם את מלאך ה' הטוב. וקצת קשה, כי הנה גם כשבלעם ראה את המלאך, לא קרה לו כלום ולא נטרפה דעתו. (פ' בלק תש\"ס)",
      "source_url": "https://www.sefaria.org/Birkat_Asher_on_Torah,_Numbers_22:23:1"
    },
    {
      "commentator_name": "נחל קדומים",
      "commentary_text": "מלאך ה' נצב בדרך. ר\"ת גימטריא מיכאל עם הכולל. גאוני קמאי בס' רבינו אפרים ז\"ל. וחרבו שלופה בידו. פירש רבינו שלמה אסתרוק ז\"ל חרבו שב אל בלעם שהמלאך הוציא חרבו של בלעם מתערה רמז לו שיהרג בחרב וז\"ש לו יש חרב בידי ר\"ל אלו לא נשלפה חרבי מתערה כי עתה כבר לקחתיך והרגתיך:",
      "source_url": "https://www.sefaria.org/Nachal_Kedumim_on_Torah,_Numbers_22:23:1"
    },
    {
      "commentator_name": "קונטרס חיבה יתירה",
      "commentary_text": "ותרא האתון את מלאך ה' ניצב בדרך. ג' פעמים ותרא האתון, תחילה ניצב המלאך לפניה והיא נטתה מן הדרך ועברה אותו, וחזר וניצב לפניה ולחצה אל הקיר ועברה אותו ושוב ניצב לפניה ורבצה במקומה, וכולן סימן לבלעם וראה בסמוך. ותט האתון מן הדרך וכן ותלחץ אל הקיר, רמז לרצון בלעם לעקוף את רצון ה' ולהרע לישראל. מלאך ה' ניצב בדרך, שעמד במקומו והם התקרבו אליו, רמז שבלעם יביא להריגת עצמו בעצתו על דבר פעור.",
      "source_url": "https://www.sefaria.org/Chibbah_Yeteirah_on_Torah,_Numbers_22:23:1"
    },
    {
      "commentator_name": "גור אריה",
      "commentary_text": "רשע זה הניח וכו'. דאם לא כן, \"וחרבו שלופה בידו\" למה, הא אין המלאך מנצח בחרב, אלא ברוח פיו ימית רשע, אלא מפני שהרשע שינה כלי אומנותו, שינה גם כן המלאך כלי אומנותו:",
      "source_url": "https://www.sefaria.org/Gur_Aryeh_on_Bamidbar_22:23:1"
    },
    {
      "commentator_name": "משכיל לדוד",
      "commentary_text": "וחרבו וכו׳ אמר רשע וכו׳ הכי איתא בבמדבר רבה דאטו לא היה יכול המלאך לנשוף בו ולהוציא רוחו אלא אם שלף חרבו והרי כתיב בסנחריב וכו׳ וכתיב נשף בהם וכו׳ אלא א״ל וכו׳ ע״כ וא״ת הא אשכחן נמי בשאר דוכתי שהמלאך בא בחרב שלופה וכדכתיב וחרבו שלופה בידו נטויה על ירושלים והתם לא דרשו ביה ולא מידי וי״ל דהתם ניחא דמלאך המות היה כדכתיב המלאך המשחית ואיהו ודאי אורחיה בהכי אבל הכא במלאך רחמים הוה כדלעיל ואינהו לאו אורחייהו בחרב ומש״ה קשיא להו והוצרכו לדרוש והתם נמי גבי סנחריב לאו מלאך המות הוה אלא גבריאל כדאי׳ בהדיא בפ׳ חלק:",
      "source_url": "https://www.sefaria.org/Maskil_LeDavid,_Numbers_22:23:1"
    },
    {
      "commentator_name": "אם למקרא",
      "commentary_text": "ותרא האתון וגו'. כדרך שאמרו רבותינו על הנסים העתידים בוא ואראך דוגמתן בעו\"הז כן אנו נאמר על שאר הנסים שגם הם יש כיוצא בהם ע\"ד טבע, כי חכמת אלהים אחת היא בשניהם בטבע ובשאחר הטבע ושניהם בחותם אחד נחתמו, ועל תבנית אחד נתקנו הרי הוא אומר שהאתון ראתה ובלעם לא ראה, וכן החוש והנסיון יעידו שיש דברים שהבהמה מרגשת בהם ולא האדם, ופעמים שהבהמה תרגיש קודם האדם, וממנה ילקח אות וראיה למה שעתיד להיות ב\"מ, ידענו כי קודם שיחל הרעש בכמו חצי שעה ויותר גם כן, רוב הבהמות מרגישים עת בואו, ונראים כמבוהלים ודחופים והשקט לא יוכלו ואין עדין שום סימן נרגש לבני אדם וכן במקרים הנסיים כשירצה ה' להכין גם שניהם להשגתם הבהמה והאדם, בהמה קודמת כאתונו של בלעם, והנה בזה תבין למה אמר ויפתח ה' את כי האתון ולא אמר ויגל ה' את עיני האתון, כי ראיית המלאך שראתה האתון לא היתה ראייה בעצם כדרך שאנחנו רואים רק הרגש פנימי חזק ונורא מאד מדבר מבהיל לא ידעה מה הוא כדרך שהבהמה מרגשת קצת דברים טרם יצאו לפעל שלם לא בכח חוש חיצוני אלא בהרגש פנימי, וזה שכל הבהמה לא זולת- כי להיות דעתה עדיין כמוס ונבלע בהנפש הכללית תרגיש בדברים הכלליים ובנפש העולם יותר משכל האדם שנתעצם להיות שכל אישיי נבדל מנפש הכללית ועומד בעצמו, על כן לא ירגיש כי אם על דרך אחרת וכדבר מוזר וחיצוני לו.",
      "source_url": "https://www.sefaria.org/Em_LaMikra,_Numbers_22:23:1"
    },
    {
      "commentator_name": "אם למקרא",
      "commentary_text": "[השמטה: ותרא האתון. עיין מה שכתבתי במקומו, ועתה אני רואה דברים יקרים לעניינינו בספר Mysteres de la Main par Desbarroles. Paris p. 190. אמרתי להעתיקם.. Si l' homme veut se mettre en rapport parfait avee la nature entiere, il laut qu' il endorme les MENS .C' est sculement par la partie commune a tous les etres qu' il peut se trouver en harmonie avec tous le etres, et l' instinct est l' harmonie de la nature entiere. Aussi les animaux pressentent ils les tempetes, les tremblements de terre, les grands cataelysmes. (On a dit des chiens qu' ils voient les fantomes et cela se peut.) Aussi les voyants sortent ils tous de la classe du peuple, et sont ils tres simples pour la plupart, et parfois idiots. Aussi les somnambules sont ils obbliges de laisser enivrer leur MENS pour lire dans la lumiere astrale. ll y a eu des hommes superieurs qui ont lu dans cette lumiere, mais il leur a fallu, comme Paracelse et Apollonius de Thyane employer des moyens particullers, il leur a fallu engourdir leur MENS en regardant fixement et costamment un seul point en se preoccupant d' une seule idee, en arretant, en un mot l' action de l' intelligence par un effort violent de Ieur volonteואולי אל ההכרח הזה להשתקע בעמקי הטבע החומרי להשיג ידיעות מוזרות ונעלות מן השכל, הוא שרמזו רבותינו באמרם שבלעם בועל אתונו היה, כוונו בזה דרך הפלגה להשקעו בחיים החומריים, ועזיבת השכל ותרדמתו endormir les MENS, או אולי בדקדוק דברו, ואלו לא ידענו מהגנוסטיקים (הכת של נוצרים שעמדו בתחלת הווסד דתם) שעשו כהנה וכהנה לתכלית זה עצמו שרמזנו למעלה, היינו תמהים על דרשת רבותינו אבל אחר שידענו תועבותיהם שכל שומעיהם תצלנה שתי אזניו, לא נפלא עוד אם רבותינו שעמדו בזמנם, וידעו מעשיהם, וחשבו את בלעם לראש ופטרון עליהם, באומרם \"לא עמדו פילוסופין לאו\"הע כבלעם וכאבנימוס הגדרי\" יחסו לבלעם מה שהיו עושים תלמידיו או כיוצא בו.]",
      "source_url": "https://www.sefaria.org/Em_LaMikra,_Numbers_22:23:2"
    }
  ]
}