{
  "perasha": "פרשת בלק",
  "chapter": 23,
  "verse": 19,
  "verse_text_hebrew": "לֹ֣א אִ֥ישׁ אֵל֙ וִֽיכַזֵּ֔ב וּבֶן־אָדָ֖ם וְיִתְנֶחָ֑ם הַה֤וּא אָמַר֙ וְלֹ֣א יַעֲשֶׂ֔ה וְדִבֶּ֖ר וְלֹ֥א יְקִימֶֽנָּה׃",
  "ref_he": "במדבר כ״ג:י״ט",
  "source_url": "https://www.sefaria.org/Numbers.23.19",
  "commentaries": [
    {
      "commentator_name": "רש\"י",
      "commentary_text": "לא איש וגו'. כְּבָר נִשְׁבַּע לָהֶם לַהֲבִיאָם וּלְהוֹרִישָׁם אֶרֶץ שִׁבְעָה אֻמּוֹת וְאַתָּה סָבוּר לַהֲמִיתָם בַּמִּדְבָּר?:",
      "source_url": "https://www.sefaria.org/Rashi_on_Numbers_23:19:1"
    },
    {
      "commentator_name": "רש\"י",
      "commentary_text": "ההוא אמר וגו'. בִּלְשׁוֹן תֵּמַהּ, וְתַרְגּוּמוֹ וְתָיְבִין וּמִתְמַלְּכִין — חוֹזְרִים וְנִמְלָכִין לַחֲזֹר בָּהֶם:",
      "source_url": "https://www.sefaria.org/Rashi_on_Numbers_23:19:2"
    },
    {
      "commentator_name": "אור החיים",
      "commentary_text": "לֹא אִישׁ וְגוֹ׳ וּבֶן אָדָם וְגוֹ׳. אָמַר שְׁתֵּי הַדְרָגוֹת כְּנֶגֶד שְׁתֵּי בְּחִינוֹת: הָאַחַת אֲשֶׁר יַבְטִיחַ הָאָדָם הַזּוּלָת עַל דָּבָר, וְהַשֵּׁנִי אֲשֶׁר יַחְכִּים אָדָם עֲשׂוֹת דָּבָר בְּהַנְהָגוֹתָיו וְעִנְיָנָיו שֶׁאֵין נוֹגְעִים לַזּוּלָת. כְּנֶגֶד מַאֲמָר שֶׁהוּא הַבְטָחַת הַזּוּלָת אָמַר לֹא אִישׁ אֵל וִיכַזֵּב, וּכְנֶגֶד מַאֲמָר שֶׁאֵינוֹ נוֹגֵעַ לַזּוּלָת אָמַר וּבֶן אָדָם וְיִתְנֶחָם, שֶׁאֵינוֹ מְכַזֵּב בַּזּוּלָת אֶלָּא יִנָּחֵם עַל אֲשֶׁר דִּבֵּר עֲשׂוֹת. וּבְמַה שֶׁלְּפָנֵינוּ יֵשׁ שְׁנֵי דְּבָרִים אֲשֶׁר דִּבֵּר ה׳: אֶחָד לְהָקִים מַלְכוּת יִשְׂרָאֵל וּלְהֵטִיב לָהֶם, וְהַשֵּׁנִי שֶׁחָשַׁב ה׳ לַעֲשׂוֹת רְצוֹנוֹ לָתֵת תּוֹרָתוֹ לְעַם קְדוֹשׁוֹ, וְהֵם דְּבָרִים שֶׁנּוֹגְעִים לוֹ יִתְבָּרַךְ. וּכְנֶגֶד שְׁנֵיהֶם אָמַר ״לֹא אִישׁ אֵל וִיכַזֵּב״ בַּהַבְטָחוֹת הַטּוֹבוֹת אֲשֶׁר הִבְטִיחַ לָאָבוֹת, ״וּבֶן אָדָם וְיִתְנֶחָם״ מִמַּה שֶׁחָשַׁב בְּהַנְהָגוֹת עוֹלָמוֹ לָתֵת תּוֹרָתוֹ לְיִשְׂרָאֵל וּלְהַדְרִיכָם לְקַיֵּם מִצְווֹתָיו. וְאִם כֵּן, אֵיךְ יַחְשֹׁב לְקַלֵּל יִשְׂרָאֵל וְנִמְצָא מְכַזֵּב חָס וְשָׁלוֹם בְּהַבְטָחוֹתָיו לָאָבוֹת וְנִחָם עַל מַה שֶׁחָשַׁב עֲשׂוֹת?",
      "source_url": "https://www.sefaria.org/Or_HaChaim_on_Numbers_23:19:1"
    },
    {
      "commentator_name": "רשב\"ם",
      "commentary_text": "לא איש אל - אינו איש לחזור מברכתו בשעה מועטת כזו, שהרי לא פשעו אחר הברכה שברכתי אותם היום.",
      "source_url": "https://www.sefaria.org/Rashbam_on_Numbers_23:19:1"
    },
    {
      "commentator_name": "רשב\"ם",
      "commentary_text": "ויכזב - והוא היאך יכזב בו בחנם.",
      "source_url": "https://www.sefaria.org/Rashbam_on_Numbers_23:19:2"
    },
    {
      "commentator_name": "רשב\"ם",
      "commentary_text": "ויתנחם - בתמיה. והיאך יתנחם?!",
      "source_url": "https://www.sefaria.org/Rashbam_on_Numbers_23:19:3"
    },
    {
      "commentator_name": "רשב\"ם",
      "commentary_text": "ולא יעשה - בתמיה.",
      "source_url": "https://www.sefaria.org/Rashbam_on_Numbers_23:19:4"
    },
    {
      "commentator_name": "פני דוד",
      "commentary_text": "לֹא אִישׁ אֵל וִיכַזֵּב וּבֶן־אָדָם וְיִתְנֶחָם הַהוּא אָמַר וְלֹא יַעֲשֶׂה וְדִבֶּר וְלֹא יְקִימֶנָּה: לא איש אל ויכזב ובן אדם ויתנחם. רש\"י פירש דכבר נשבע להביאם לארץ וכו'. ואפשר במאי דקי\"ל דהאומר לתת מתנה מועטת לחבירו וחזר בו הוא מחוסר אמנה דשארית ישראל לא יעשו עולה ולא ידברו כזב כמו שפירש\"י במציעא דף מ\"ט. ומתנה מרובה מותר דלא סמכה דעתיה ואם רבים אמרו לתת מתנה מרובה יש בו משום מחוסרי אמנה כמבואר בח\"מ סי' ר\"ד ז\"ש לא איש אל ויכזב שיחזור מלתת הארץ לישראל כמו שפירש\"י וזהו ויכזב דהחוזר בו מחוסר תואר לא ידברו כזב. וכי תימא מתנת הארץ מתנה מרובה ומותר לחזור בו. לז\"א ובן אדם ויתנחם כלומר וכי דינו כבן אדם יחיד שיוכל להתנחם. והרי אם רבים אינם יכולים ק\"ו לו יתברך וזהו ובן אדם יחידי ויתנחם:",
      "source_url": "https://www.sefaria.org/Penei_David,_Numbers,_Balak_6:1-2"
    },
    {
      "commentator_name": "רבנו בחיי",
      "commentary_text": "לא איש אל ויכזב. בדבריו שאמר לי לא תאור את העם, א\"כ איך תוכל לומר וקבנו לי משם.",
      "source_url": "https://www.sefaria.org/Rabbeinu_Bahya,_Bamidbar_23:19:1"
    },
    {
      "commentator_name": "רבנו בחיי",
      "commentary_text": "ההוא אמר ולא יעשה. אם הוא חוזר להקב\"ה יהיה בתמיה, ואם בברור ובלשון ידיעה יחזור לבן אדם שהזכיר שהוא מתנחם כי הוא אומר ולא יעשה ומדבר ולא מקיים ולא כן הקב\"ה שהוא גוזר ומקיים. ובמדרש לא איש אל ויכזב, לפי שצפה בלעם שעתיד אדם אחד (בישמעאל) להטעות את העולם ולומר שהוא נביא התחיל צווח איש נעשה נביא עתיד הוא להתנחם ואומר דבר ואינו יכול לעשותו שנאמר ההוא אמר ולא יעשה. לא איש אל ויכזב, בטובה, אבל כשהוא אומר להביא רעה חוזר בו, שנאמר ההוא אמר ולא יעשה, תדע לך שהרי אמר לאברהם (בראשית ט״ו:ה׳) וספור הכוכבים, ונתקיים, שנאמר (דברים א׳:י׳) והנכם היום ככוכבי השמים, זהו לא איש אל ויכזב, בטובה, אבל ברעה ההוא אמר ולא יעשה, אמר לישראל (הושע א׳:ט׳) כי אתם לא עמי, חזר ואמר (שם ב) ואמרתי ללא עמי עמי אתה, הוי אומר ההוא אמר ולא יעשה, כך דרשו בתנחומא.",
      "source_url": "https://www.sefaria.org/Rabbeinu_Bahya,_Bamidbar_23:19:2-3"
    },
    {
      "commentator_name": "תורה תמימה על התורה",
      "commentary_text": "לא איש אל וגו׳. ת\"ר, שלשה אין ממצעין ולא מתמצעין, הכלב והדקל והאשה, ויש אומרים, אף החזיר, וי\"א אף הנחש, ואי ממצעין כאי תקנתיה, אמר רב פפא, נפתח באל ונפסוק באל חר\"ל פותח בפסוק (כ\"ב) אל מוציאם ממצרים לא הביט און ביעקב וכו' עד מה פעל אל. , אי נמי נפתח בלא ונפסוק בלא טבפסוק לא איש אל ויכזב עד ולא יקימנה, וטעם הענין משום דכל הני דאין ממצעין ומתמצעין הוא משום כישוף, ופסוקים אלו מורים שאין נחוש בישראל. – ועיין בהוריות י\"ג ב' דחשיב שם בין הדברים המשכחים את הלמוד גם הא דהעובר בין שתי נשים או אשה העוברת בין שני אנשים, ולכי מש\"כ י\"ל בטעם הדבר ע\"פ מש\"כ חכמי האמת דהעוסק בכשפים ונחושים לבו מתטמטם לת\"ת, ומכיון שהעברה כזו גורמת לכשפים כמש\"כ, לכן ממילא גורמת גם לשכחת הלמוד. .(פסחים קי\"א א׳)",
      "source_url": "https://www.sefaria.org/Torah_Temimah_on_Torah,_Numbers_23:19:1"
    },
    {
      "commentator_name": "תורה תמימה על התורה",
      "commentary_text": "לא איש אל וגו'. רבנן אמרי, לא איש הוא שעשה דבריו של אל כמו שאינן, כמ\"ש (פ׳ תשא) למה ה׳ יחרה אפך בעמך, ובן אדם ויתנחם, לא בן עמרם הוא שעשה לאל שיתנחם כמ\"ש (שם) וינחם ה׳ על הרעה אשר דבר לעשות לעמו יכמה דרשות במדרשים ואגדות על פסוק זה, והדורש הזה כנראה מפרש שאחרי שהטריח בלק את בלעם כמה פעמים לבצע מחשבחו הבטיחו בלעם שלחנם כל עמלו, יען כי לו גם אם יוציא זעמו לקלל את ישראל גם אז לא יועיל, כי כבר ראו לדעת כי בכח אדם צדיק לפעול מהקב\"ה להפך מחשבתו על ישראל מרעה לטובה כאשר עשה משה וכמש\"כ ותגזר אומר ויקם לך, הקב\"ה גוזר וצדיק מבטלה, וכהראיות שמביא בזה. .(ירושלמי תענית פ\"ב ה\"א)",
      "source_url": "https://www.sefaria.org/Torah_Temimah_on_Torah,_Numbers_23:19:2"
    },
    {
      "commentator_name": "ריב\"א",
      "commentary_text": "לא איש אל ויכזב. ובן אדם ויתנחם הוא לשון חרפה בלע\"ז אישיר\"יפונטא וכבר פירשתי זה בפרשת בראשית:",
      "source_url": "https://www.sefaria.org/Riva_on_Torah,_Numbers_23:19:1"
    },
    {
      "commentator_name": "שפתי חכמים",
      "commentary_text": "בלשון תימה. כלומר, וכי הקב\"ה אמר ולא יעשה ודבר ולא יקימנו:",
      "source_url": "https://www.sefaria.org/Siftei_Chakhamim,_Numbers_23:19:1"
    },
    {
      "commentator_name": "שפתי חכמים",
      "commentary_text": "חוזרין ונמלכים לחזור בהם. כלומר תרגומו של ויתנחם תייבין ומתמלכין, ופירושו חוזרין ונמלכין לחזור בהן והוא מדברי רש\"י ז\"ל. ולפי התרגום אינו ל' תמיה, כלומר בני אדם דרכם בכך אבל לא הקב\"ה:",
      "source_url": "https://www.sefaria.org/Siftei_Chakhamim,_Numbers_23:19:2"
    },
    {
      "commentator_name": "רלב\"ג ביאור המלות",
      "commentary_text": "לא איש אל ויכזב. הרצון בו למה תחשוב שיסכים עתה השם יתעלה לקללם וכבר גלה דעתו קודם זה שאין רצונו לקללם כאמרו מה אקוב לא קבה אל הנה השם יתעלה אינו במדרגה שיכזב בדבריו כי אין אצלו כי אם אמת ואינו מתחרט גם כן ממה שגמר בלבו לעשותו כי אינו בן אדם שיתנחם האם הוא יתע' אמר לעשות דבר ולא יעשהו או דבר דבר ולא יקימנו.",
      "source_url": "https://www.sefaria.org/Ralbag_Beur_HaMilot_on_Torah,_Numbers_23:19:1"
    },
    {
      "commentator_name": "אור החיים",
      "commentary_text": "וְאָמְרוֹ ״וִיכַזֵּב״ ״וְיִתְנֶחָם״ בְּתוֹסֶפֶת וָא״ו, כָּלַל בָּזֶה שְׁתֵּי הַדְרָגוֹת: אַחַת, שֶׁאֵינוֹ אִישׁ וְלֹא אָדָם, וְעוֹד לַחְשֹׁד בּוֹ חָס וְשָׁלוֹם דָּבָר שֶׁאֲפִלּוּ בַּנִּבְרָאִים הוּא גֵּרָעוֹן, וְהוּא הַכָּזָב וְהַחֲרָטָה. וְנִתְכַּוֵּן בָּזֶה שֶׁמִּן הַנִּמְנָע שֶׁיַּסְכִּים עַל קִלְלַת יִשְׂרָאֵל עַד שֶׁיִּהְיוּ בּוֹ שְׁנֵי דְּבָרִים: ״אִישׁ וִיכַזֵּב״ וּ״בֶן אָדָם וְיִתְנֶחָם״, שֶׁהֲגַם שֶׁהָיָה חָס וְשָׁלוֹם אִישׁ וִיכַזֵּב, עִם כָּל זֶה לֹא יִתְחָרֵט לְמַה שֶׁנוֹגֵעַ לְמַה שֶׁחָשַׁב עֲשׂוֹת רְצוֹנוֹ בְּאֶמְצָעוּת יִשְׂרָאֵל. וְטַעַם שֶׁפַּעַם אַחַת אָמַר ״אִישׁ״ וּפַעַם אַחַת אָמַר ״בֶּן אָדָם״, לְפִי שֶׁהַמַּבְטִיחַ לְהֵטִיב לַזּוּלַת יֶשְׁנוֹ בְּגֶדֶר מַעֲלָה, לָזֶה אָמַר לְשׁוֹן חֲשִׁיבוּת, וּבִפְרָט הַמִּתְחָרֵט עַל מַה שֶׁחָשַׁב עַל עַצְמוֹ אָמַר ״וּבֶן אָדָם״.",
      "source_url": "https://www.sefaria.org/Or_HaChaim_on_Numbers_23:19:2"
    },
    {
      "commentator_name": "אור החיים",
      "commentary_text": "הַהוּא אָמַר וְגוֹ׳. פְּשַׁט הַכָּתוּב חוֹזֵר לְהָאָדָם, וְאֶפְשָׁר לְפָרְשׁוֹ עַל הַקָּדוֹשׁ בָּרוּךְ הוּא עַל זֶה הַדֶּרֶךְ: כְּשֶׁרוֹצֶה לַעֲשׂוֹת מַעֲשֶׂה אֵינוֹ צָרִיךְ לְמַעֲשֶׂה אֶלָּא בְּמַאֲמָר הוּא נַעֲשֶׂה, וְהוּא אָמְרוֹ הַהוּא – פֵּרוּשׁ, הָאֵל שֶׁהִזְכִּיר בְּסָמוּךְ, ״אָמַר״ – פֵּרוּשׁ פְּעֻלּוֹתָיו שֶׁעָשָׂה הוּא אָמַר וַתֶּהִי, וְלֹא יַעֲשֶׂה – פֵּרוּשׁ לֹא יִצְטָרֵךְ לְמַעֲשֶׂה, כְּאָמְרוֹ (בראשית א:ג) ״וַיֹּאמֶר וְגוֹ׳ וַיְהִי כֵן״, וְכֵן אָמְרוּ בַּמִּשְׁנָה (אבות ה:א) ״בַּעֲשָׂרָה מַאֲמָרוֹת נִבְרָא הָעוֹלָם״. וְאָמְרוֹ וְדִבֶּר וְגוֹ׳ – פֵּרוּשׁ וּכְשֶׁהַמַּעֲשֶׂה שֶׁנַּעֲשָׂה בְּמַאֲמָרוֹ אֵינוֹ כָּל כָּךְ קַיָּם, עַל דֶּרֶךְ אָמְרָם שֶׁהָיָה הָעוֹלָם רוֹפֵף וְרוֹעֵד, דִּכְתִיב (איוב כו:יא) ״עַמּוּדֵי שָׁמַיִם יְרוֹפָפוּ וְיִתְמְהוּ מִגַּעֲרָתוֹ״, וְאָמְרוּ חֲכָמֵינוּ זִכְרוֹנָם לִבְרָכָה (חגיגה יב.) שֶׁגָּעַר ה׳ בָּהֶם וְנִתְקַיְּמוּ, וְהוּא אָמְרוֹ וְדִבֶּר לְשׁוֹן קוֹשִׁי, וְלֹא יְקִימֶנָּה – פֵּרוּשׁ וְלֹא יִצְטָרֵךְ לְקַיְּמֶנָּה אֶלָּא בְּדִבּוּרוֹ הַקָּשֶׁה הִיא מִתְקַיֶּמֶת וּמִתְחַזֶּקֶת.",
      "source_url": "https://www.sefaria.org/Or_HaChaim_on_Numbers_23:19:3"
    },
    {
      "commentator_name": "ביאור שטיינזלץ",
      "commentary_text": "לֹא אִישׁ הוא האֵל – וִיכַזֵּב, ולא יעמוד בדבריו, ולא בֶן אָדָם, העשוי להתחרט – וְיִתְנֶחָם. האם הוּא, האל אָמַר – וְלֹא יַעֲשֶׂה?! וְהאם הוא דִבֶּר – וְלֹא יְקִימֶנָּה, יקיים את דברו ?!",
      "source_url": "https://www.sefaria.org/Steinsaltz_on_Numbers_23:19"
    },
    {
      "commentator_name": "שפתי כהן",
      "commentary_text": "עוד במדרש. לא איש אל ויכזב, אינו כבשר ודם שקנה אוהבים ומצא אחרים יפים מהם, כופר בראשונים. ההוא אמר וגו', כשהוא אומר להביא עליהם רעה עשו תשובה מבטלה, אתה מוצא כתוב זובח לאלהים יחרם ועשו את העגל והם ראוים לכליה ועשו תשובה ובטל הגזרה מעליהם שנאמר וינחם ה', ואיך אתה סבור לקללם ולהכחידן:",
      "source_url": "https://www.sefaria.org/Siftei_Kohen_on_Torah,_Numbers_23:19:1"
    },
    {
      "commentator_name": "שפתי כהן",
      "commentary_text": "עוד לא איש אל ויכזב. כשמיעד על הטובה אפילו על תנאי מקיימה אבל על הרעה מתנחם כשעושין תשובה, זהו ובן אדם, כלו' כשרואה עצמו שהוא אדם המין המעולה והמובחר שנאמר אדם אתם ועושה תשובה, אז ויתנחם:",
      "source_url": "https://www.sefaria.org/Siftei_Kohen_on_Torah,_Numbers_23:19:2"
    },
    {
      "commentator_name": "שפתי כהן",
      "commentary_text": "עוד לא איש אל ויכזב, לפי שפעם ראשונה ברכם ואמר כי מראש צורים אראנו, פירוש אני רואה אב ובן עלו, האב לזבוח והבן להזבח ושם נאמר לו כי ברך אברכך ויירש זרעך את שער אויביו, ואם נקלל נהיה אויבים ויירשונו, כי לא איש אל ויכזב. ומגבעות, בגימט' ז\"ה יצח\"ק רבק\"ה, שנאמר לו כי לך ולזרעך אתן את כל הארצות האל והקימותי את השבועה אשר נשבעתי לאברהם, והוא מה שאמר ויירש זרעך את שער אויביו, א\"כ א\"א לבא כנגדם, לזה אמר ובן אדם ויתנחם, שאם היה מתנחם לא היה חוזר פעם שנית ומקיימה ליצחק, וכנגד מה שאמר הן עם לבדד ישכון כנגד זה אמר ההוא אמר ולא יעשה, הרי נאמר וישכון ישראל בטח בדד עין יעקב. וכנגד מה שאמר ובגוים לא יתחשב, שלא יתחשב בגוים שנאמר עליהם והיו עמים משרפות סיד וגו', כנגד זה אמר ודבר ולא יקימנה, א\"כ הנה ברך לקחתי, מאחר שפעם ראשונה לקחתי כתרגומו קבלית, ועתה בפעם שנית קיימה, זהו וברך פעם ראשונה, הנה ברך עתה בפעם שניה נתקיימה ולא תשוב עוד מהם הברכה לעולם, למה כי לא איש אל ויכזב:",
      "source_url": "https://www.sefaria.org/Siftei_Kohen_on_Torah,_Numbers_23:19:3"
    },
    {
      "commentator_name": "שפתי כהן",
      "commentary_text": "שמעתי על דרך מליצה, שאמר בלעם שקודם על שהלך על דעת לקלל, נעשה חיגר בוקא דאטמא דשף מדוכתיה, עתה שלקחתי וקבלתי עלי לברך וברכתי, למה לא תשוב בוקא למקומה, זהו ולא אשיבנה ולשון וברך כמו כי לך תכרע כל ברך. ובזהר ולא אשיבנה, ולא אשיבנו מבעיא ליה, אלא לא אשיבה לההוא דכתיב וכה תדבר, לית אנא יכיל לאהדרא לה, ע\"כ:",
      "source_url": "https://www.sefaria.org/Siftei_Kohen_on_Torah,_Numbers_23:19:4"
    },
    {
      "commentator_name": "אבן עזרא",
      "commentary_text": "אמר ולא יעשה. אמרו:",
      "source_url": "https://www.sefaria.org/Ibn_Ezra_on_Numbers_23:19:1"
    },
    {
      "commentator_name": "אבן עזרא",
      "commentary_text": "ודבר. דברה:",
      "source_url": "https://www.sefaria.org/Ibn_Ezra_on_Numbers_23:19:2"
    },
    {
      "commentator_name": "העמק דבר",
      "commentary_text": "לא איש אל ויכזב. כבר ביארנו דשם אל הוא כח ההנהגה. והנה נהיו ישראל לעם סגולה להנהיג בהם את עולמו ע״פ התורה והמצוה שלהם. וזהו גדולתן של ישראל. ואמר בלעם דזה א״א לשנות כי מתחלת בריאת שו״א רצה הקב״ה להשכין שכינתו בארץ. אלא שלא הגיעה העת ליתן התורה וע״כ נקרא כל אותו העת שני אלפים תהו כדאיתא בע״ז דף ח׳ והיינו כשני ילדות של הבן שאין האב יכול להנהיג ביתו על פיו עד שיגדל ויגיע לדעת. כך היה העולם תהו עד שבא אברהם אבינו ולמד תורה והיה הוא וביתו בהשגחה פרטית ואחר כך קבלו ישראל את התורה. אז נגמר רצון השגחת ה׳ שהיה בבריאת שו״א. וע״ז אמר בלעם דכח אל לא איש הוא ויכזב שיהא נפסק כמו מים כוזבים. וא״א להפסיק השגחת ה׳ בעולם אשר א״א אלא ע״י ישראל:",
      "source_url": "https://www.sefaria.org/Haamek_Davar_on_Numbers_23:19:1"
    },
    {
      "commentator_name": "העמק דבר",
      "commentary_text": "ובן אדם ויתנחם כמו התולדות של אדם נקרא בני אדם. כך תולדות הנהגה העיקרית מה שמצטרף לה מכונה בן ואמר בלעם לענין עקירת שבעה אומות בני הקדם שכבר נגזר לצרף להשגחה על ישראל וא״א להתנחם. דכל התנחמות בגזרת ה׳ אינו אלא ע״י תפלה ותשובה שמעבירין את הגזרה. ואין זה חרטה ח״ו אלא כך הטביע הקב״ה את העולם שתהא תפלה מבטלת הגזרה משא״כ בלי חידוש מעשים כמו שבעה אומות שלא הרבו תשובה ותפלה. א״א להתחרט. ופי׳ עוד ההוא אמר. לענין דבר ראשון אמר בלעם ההוא אמר בעשרה מאמרות של בריאת שמים וארץ:",
      "source_url": "https://www.sefaria.org/Haamek_Davar_on_Numbers_23:19:2"
    },
    {
      "commentator_name": "העמק דבר",
      "commentary_text": "ולא יעשה. לא יעמיד העולם על מתכונתו [ובכ״מ משמעות עשיה הוא גמר ותיקון גמור כמש״כ בספר ויקרא י״ט ה׳]:",
      "source_url": "https://www.sefaria.org/Haamek_Davar_on_Numbers_23:19:3"
    },
    {
      "commentator_name": "העמק דבר",
      "commentary_text": "ודבר. לגזירה על שבעה אומות:",
      "source_url": "https://www.sefaria.org/Haamek_Davar_on_Numbers_23:19:4"
    },
    {
      "commentator_name": "העמק דבר",
      "commentary_text": "ולא יקימנה. כמו שנגזר. וא״כ א״א להשתנות שני דברים אלו:",
      "source_url": "https://www.sefaria.org/Haamek_Davar_on_Numbers_23:19:5"
    },
    {
      "commentator_name": "בכור שור",
      "commentary_text": "לא איש אל ויכזב. כזב קורא מי שחוזר בדבורו בחנם שיש ספק בידו לעשות מה שאמר והוא אינו עומד בדבורו וחוזר בו בחנם, זהו כזבן, אבל הק' אינו כן, וכן אדם ויתנחם כמו אדם שאין ספק לעשות מה שאמר ומתנחם על מה שאמרו אבל הק' כל יכול ואלו שתי מדות אינם מצויות בהק', אבל יש מידה שלישית כגון אדם שאומר לחבירו אני נותן לך כך וכך בשביל שתכבדינו ותעבדינו וזה אינו רוצה לעבוד ולכבד והוא מתנחם מלתת לו וזאת הנחמה בפשיעת המקבל שלא מילא תנאו, והנותן אמיתי ועמד בדבורו שלא התנה אלא על מנת, וכן גבי רעה שאדם אומ' להרע לחבירו ובא זה ופייסו ואינו עושה לו רע: זה מצוי בהק' - כי הדין עמו - כמו גבי אדם דכתי' \"כי נחמתי כי עשתים\" שאני בראתים לכבודי כדכתי' \"כל הנקרא בשמי לכבודי בראתיו\" וגו' והם השחיתו דרכם לכך נחמתי על פשיעתם וכן \"נחמתי כי המלכתי את שאול למלך כי שב מאחרי\" ואני אמרתי לו על ידי שמואל \"והיתם גם אתם וגם המלך אשר מלך עליכם אחרי ה' אלהיכם\" והוא שב מאחרי, וכן במדה רעה כמו בנינוה ובישראל ששבו מדרכם הרעה ומן החמס \"וינחם ה' על הרעה\" וכן הוא אומ' ודוד \"אם ישמרו בניך את דרכם\" וכן פי' בבראשית כי [ג' נחמות מצויות באדם, אחת שאינו עומד בדבורו ואחת שאינו יכול ואחת בפשיעת המקבל ועל השנים אמר בלעם] שאינו בהק' נחמת כזב ונחמת שאינו יכול ולכך מתמה ואומ' ההוא הק' אמר ולא יעשה וגו' בתמיה:",
      "source_url": "https://www.sefaria.org/Bekhor_Shor,_Numbers_23:19:1"
    },
    {
      "commentator_name": "חזקוני",
      "commentary_text": "לא איש אל ויכזב אינו איש לחזור מברכתו כיון שברכתים היום בשמו שהרי לא פשעו.",
      "source_url": "https://www.sefaria.org/Chizkuni,_Numbers_23:19:1"
    },
    {
      "commentator_name": "חזקוני",
      "commentary_text": "ובן אדם ויתנחם שלש נחמות מצויות, אחת במי שאינו עומד בדבורו, ואחרת במי שאינו יכול, והשלישית בפשיעת המקבל ועל השתיים אמר בלעם ובן אדם ויתנחם.",
      "source_url": "https://www.sefaria.org/Chizkuni,_Numbers_23:19:2"
    },
    {
      "commentator_name": "מנחת שי",
      "commentary_text": "ויכזב. הזי\"ן דגושה:",
      "source_url": "https://www.sefaria.org/Minchat_Shai_on_Torah,_Numbers_23:19:1"
    },
    {
      "commentator_name": "אבי עזר",
      "commentary_text": "בפסוק ההוא אמר ולא יעשה. בפרשת עקב תראה כוונתו בס\"ד:",
      "source_url": "https://www.sefaria.org/Avi_Ezer,_Numbers_23:19:1"
    },
    {
      "commentator_name": "מזרחי",
      "commentary_text": "תייבין ומתמלכין חוזרין ונמלכין לחזור בהם. בא לפרש דברי המתרגם שתרגם ויתנחם תייבין' ומתמלכין שלא פירוש ההמלכ' הזאת אם נחזור בהם אם לקיים דבריה' ופירוש חוזרין ונמלכין לחזור בהם לא שבא לפרש מלת תייבין כי זה אינו צריך ביאור:",
      "source_url": "https://www.sefaria.org/Mizrachi,_Numbers_23:19:1"
    },
    {
      "commentator_name": "הכתב והקבלה",
      "commentary_text": "לא איש אל ויכזב וכן אדם ויתנחם. הזכיר שני תוארים אדם איש, והגביל לכ\"א פחיתות מיוחד, לזה הכזב ולזה הנחמה, כי יש הבדל בין שני תוארים אלה, כדאיתא במכדרשב\"י (פ' תזריע) תנא בכמה דרגין אתקרי בר נש אדם, גבר, אנש, איש, גדול שבכולם אדם דכתיב ויקרא את שמם אדם ביום הבראם. ואין כוונת מאמר זה שתואר אדם תמיד יורה על הצדיק, ותואר איש על רע מעללים, כי הרבה מקראות יורו ההפך, ככתוב זה חלק אדם רשע, במות אדם רשע, פדני מעשק אדם, והפוכו ויעקב איש תם, נח איש צדיק, משה איש אלהים; ונ\"ל בהבדל שני תוארים אלה, כי עינינו הרואות שפרטי בני אדם נבדלים זה מזה במדותיהם מצד טבעם, וזה אמנם בא להם מצד התחלפות מזגי טבעם היסודית, כי הארבע יסודות ארמ\"ע מולידים פחיתיות באדם (וכמ\"ש בעלי הרמז אויבי איש אנשי ביתו, והם יסודותיו והרכבת גופו), ומסבתם האדם קרוב לבא לידי עברה, אם התמזגו בו שלא בדרך השווי ואין ערך ראוי ביניהם; והתמזגות יסודות האלה תתחזק ותחלש לדעת רז\"ל כפי חוזק וחולשת המזל שנולד בו, יש שלפי מזלו יתמזגו בו היסודות הטבעיות להיות נטיית מזגו לטוב ויש להפוכו, כמאמרם האי דמאן דבמאדים יהא שופך דמים, האי מאן דבצדק יהא גבר צדקן, וכפי התחלפות מזגי טבעי בני אדם ומדותיהם כן יתחלפו תוארי שמותיהם, מי שנטיית מזגו נוטה לרעה יתואר לדעתי בשם אדם, ומי שנטיית מזגו נוטה לטוב יתואר בשם איש, לפי שהאדם אשר נטיית מזגו נוטה לרע יותר, היא באה לו מצד הרכבת יסוד גשמיותו אשר בעפר ואדמה יסודם, לכן יתואר בשם אדם, כי מן האדם לוקח והורכב מן היסוד העפרי יותר מחלק רוחניותו; ואם מזג טבעו נוטה לטוב יותר, זה יורה שהרכבתו הרוחנית מתגברת בו יותר מיסודי גשמיותו, לכן יתואר ע\"ש הרכבתו זאת המתגברת בו ביתר עז בשם איש, והוא חלק רוחניותו אשר לה ישיות וקיום נצחי; לכן צבאי מרום יתוארו איש, כמו איש אל עבר פניו ילכו, איש לבוש הבדים, והאיש גבריאל, ועל הבורא ית' אמר ה' איש מלחמה, וז\"ש רז\"ל במכילתא הנזכרת שהמתואר בשם אדם הוא במעלה יותר גבוה מהמתואר בשם איש, שהמתואר בשם אדם יש לו מצד בריאותו בחינת יתרון על המתואר בשם איש, שלפי שיתרון האדם על כל הברואים אינו אלא במה שהבחירה בידו לבחור בטוב ובהפוכו, אשר מצד בחירתו זאת יוכל להשתלם ולהתעלות במעלה רמה, ולזה יותר שיש לו מתנגד מצד טבעו המטהו לרע יותר מעשיו חשובים אם יתגבר נגד טבעו; אמנם האיש אשר מצד טבעו יותר נוטה לטוב אין מעשה עבודתו חשובה כ\"כ; ולסבה זו הם נבדלים ג\"כ בשכרם וענשם, כי המתואר בשם אדם בלתי ספק ששכרו מרובה אם יצדיק מעשיו, מצד התקוממותו נגד טבעו הרע והתגברותו עליו, משא\"כ בהמתואר בשם איש שמצד טבעו אין לו התנגדיות, וכן להפך המתואר בשם אדם אם ירשיע אין ענשו גדול כ\"כ כאיש הרשע, כי לפום צערא אגרא, והכל לפי רוב המעשה; ומה נכונים בזה דברי מיסדי תפלותינו בתפלת ר\"ה באמרם. אשרי איש שלא ישכחך ובן אדם יתאמץ בך: אמרו בשבח האיש אם לא ישכח את ה', ושבח האדם אם יתאמץ בך, כי להיות שהמתואר בשם איש אשר לפי המבואר נטיית טבעו יותר לטוב הנה הוא מעותד להוציא נטיותיו מן הכח אל הפועל ולבחור בטוב, אם עד\"מ מצד טבעו יש לו מדת רחמנות שלא יוכל לראות חברו משוקע בצער וירחמהו ויחזקהו בעניו, הנה בזה אינו נקרא עובד ה' מצד הבחירה כ\"א עובד ה' מצד טבעו, וכן המתואר באדם אשר לפי המבואר נטוי יותר לתאוות מגונות אפשר שיתגבר להחליש כח תאוותיו מצד פניות חיצוניות, יתרחק עד\"מ מן הגזל מחמת יראת שופטי המדינה, יכניע תאות המשגל מצד גנות הבריות עליו וכדומה מכוונות נפסדות שאין בהם בחינת חלק עבודת ה', לכן נתנו השבח להמתואר בשם איש אם לא ישכח את ה', ר\"ל שבוחר בטוב מצד צווי הבורא ית' עליו לא מצד טבעו, ושבח המתואר בשם אדם הוא אם יתאמץ ויתגבר על כחותיו המתאוויות שבו לא מצד פניות חיצוניות כ\"א מצד שרוצה להתדבק בו ית' ובמדותיו, משא\"כ באיש שאין לו צורך התגברות זו. ועז\"א שלמה. עיר פרוצה אין חומה איש אשר אין מעצר לרוחו. ירצה כמו שאין חשיבות לגבור בכבשו עיר פרוצה וכדומה, שהיא קל הכבישה שאין ליושבי' מגן וצנה לקום בעזרתם, ככה אין חשיבות למי שמתואר בשם איש, לפי שאין מעצר ומונע בו מצד טבעו, ואין מזג טבעו מנגדו מלילך מישרים; ולהפך אמר המשורר. לפעלות אדם בדבר שפתיך אני שמרתי ארחות פריץ. ירצה מה שהוא צורך לאדם (והוא שממזג טבעו נוטה אל החמריות הרע וכמו שהי' דוד בטבעו, מעדות הכתוב אדמוני עם יפה עינים) לעשות ולשמור מצות ה' שהם מוצא פיו ית', אני על משמרתי עמדתי תמיד להתנהג כדרך שיתנהג הפריץ, שעומד בזרוע נגד מתקוממיו, כמו ובני פריצי עמך, ופריץ חיות בל יעלנה, המתפרצים על אדוניהם, שכולם יורו על העושה בזרוע רמה נגד המוחה בידו, ככה עשיתי אנכי בהתנהגי נגד כחות המתאוות הרוצים מטבעם להתגבר בקרבי בכל מה שנוגע בדבר שפתיך; ומזה אמר החכם. מפרי פי איש ישבע טוב וגמול ידי אדם ישיב לו. אמר השכר הוא להמתואר בשם איש, שיאכל כפי פרי מעלליו, והמתואר בשם אדם שכרו כגמול ידיו, כי האיש והאדם דומים לענין שכרם לשנים שנשכרו, זה לנטוע אילן שצריך יגיעה לנטעו ולשמרו בעת גדולו מכל דבר המפסידו, וזה לא קבל עליו כ\"א שמירת פירות אילן אחר שכבר גדל כל צרכו, אשר אין מן הספק ששכר פעולתם איננו שוה, האחרון לא יקבל כ\"א שכר שמירת פירות בעלמא, והראשון יקבל כגמול מעשי ידיו ולפי עמלו ביגיעת כפים בנטיעתו, ככה האיש אשר בטבעו נטוע שרש המסייעו לכל דבר טוב, ואינו צריך כ\"א לשמור נטע טבעו לבל יתקלקל להטות אחרי בצע תאוות הזמניות, ולזה לא יאכל כ\"א הפרי ממעשיו ומדותיו, אמנם המתואר בשם אדם, צריך תחלה לעקר ולשרש שרשי טבעו הרעים אשר פורים רוש ולענה, ולנטוע תחתיהם שרשים אחריהם להצמיח בם עץ החיים אשר ישא פרי השלמות ואשר יאכל אותם בזה וחי בהם לעולם, לכן שכרם עפ\"י פעולתם, האיש לא יקבל כ\"א שכר הפירות לפי ששמר נטע טבעו שלא יתקלקלו עליו פירותיו, והאדם יקבל שכר עמלו ביגיע כפיו לעקור שרשיו הרעים ולנטוע תחתיהם שרשים טובים ומועילים, וע\"ז אה\"כ מפרי פי איש ישבע טוב, ירצה האיש ישבע טובו מצד הפרי, וגמול ידי אדם ישיב לו, רצונו האדם יקבל גמול ידיו שעשה בפועל כפיו; דומה לזה אמר איוב. כי פועל אדם ישלם לו וכאורח איש ימציאנו. אמר באדם שישולם לפי הפועל, שהוצרך להשתדלות רב לעשות דרך חדש בנפשו אשר בה מסלה לעבודת אלהי', אמנם באיש אמר שיקבל שכרו לפי ארחו, כי דרכו מוכן לפניו מטבעו המטהו יותר אל המעלותיות (ובזה יתיישב סתירת מאמרי רבותינו, שהעיר עלי' מהר\"י אדרב\"י, דבתלמוד אמרו במקום שבעלי תשובה עומדים אין צדיקים גמורים יכולים לעמוד. ובמדרש אמרו ע\"פ אשרי אדם לא יחשוב ה' לו עון, אר\"ש ב\"ל מלה\"ד למי ששתת אמו מים המרים ונמצאת טהורה אמר לפני ב\"א אשרי אימא ששתת מים המרים ונמצאת טהורה, אמר ליה אדם אחר אשרי אימא שלא נצרכה לשתותם כל עיקר. הרי שצדיק גמור יותר מעולה מבע\"ת. ולדברינו ניחא דנגד צדיק גמור שהי' מתולדתו במדרגת איש, הבע\"ת יותר מעולה ממנו. אמנם אם הצדיק הגמור הי' מתולדתו במדרגת אדם, אין ספק שהוא יותר מעולה מבעלי תשובה ושפיר נאמר עליו אשרי אדם לא יחשוב ה' לו עון), וכאן אמר כי לא איש אל ויכזב ובן אדם ויתנחם, כי המתואר בשם איש כיון שמטבעו נוטה יותר אל המעלותיות, אם הוא יבטיח לחברו להיטיב עמו אין מן הספק שישתדל בכל עוז לשמור מוצא שפתיו ולשמור מבטחו, כי גם טבעו תכריחהו על כך ואין בו חשש פן יתנחם על הטובה אשר דבר לעשות עם רעהו, אמנם מניעה מבחוץ תוכל להולד אשר ממנה יסובב לבלתי מלאת דבריו לטובה. אמנם המתואר בשם אדם כיון שנטיית טבעו יותר נוטה אל הפחיתיות הנה מלבד שאין מבטח עליו מצד תולדת מניעה שחוץ ממנו, כי יוכל להיות שיתילד בו מעצמו המניעה מהשלים דבורו, והיא הנחמה שתתרומם כעת עליו נטיית טבעו הפחיתית ותמנעהו מלשמור מוצא שפתיו, ואמר קרא שאין בו ית' חשש חסרון הבטחון אשר לאיש והוא הכזב ר\"ל ההפסק וחסרון היכולת (כמו לא יכזבו מימיו) ועז\"א כי לא איש אל ויכזב, וכן אין בו ית' חשש חסרון בטחון אשר ישנו באדם והיא הנחמה, ועז\"א ובן אדם ויתנחם. ובמטות ע\"פ תתחטאו (ל\"א כ') ובר\"פ וזאת הברכה ידובר עוד מזה הענין:",
      "source_url": "https://www.sefaria.org/HaKtav_VeHaKabalah,_Numbers_23:19:1"
    },
    {
      "commentator_name": "חומת אנך",
      "commentary_text": "לא איש אל ויכזב. פירוש האיש שהולך בשליחות האל נקרא איש אל ואם כן צריך שיהיה איש אמת ולא יכזב. וכן בן אדם אלהי שיתנחם. והנה אמרתי אשר ידבר ה׳ אדבר לא נכון לכזב. כעת יאמר ליעקב מה פעל אל פירוש מהעת הזו יראה לישראל כמה חיבה נודעת להם מהאל והוא על דרך שאמר עמי זכר נא מה יעץ בלק מלך מואב וכו׳ הרב הגדול כמהר״ר וידאל הצרפתי ז״ל בפירושו כ״י:",
      "source_url": "https://www.sefaria.org/Chomat_Anakh_on_Torah,_Numbers_23:19:1"
    },
    {
      "commentator_name": "אדרת אליהו",
      "commentary_text": "מהדורא רביעאהלא איש וגו'. כי דבר שלא יקויי' הוא בב' דברי' אם מפני שבשעת מעשה מכזב לו ולבו בל עמו בשעת הבטחה או שהבטיח בלב שלם רק שאח״ז מתנחם וז״ש לא איש. והן הגדולים וכמ״ש אליכם אישים כו' ואין דרכם להתנחם אם הבטיחו בלב שלם רק שמעיקר' בלב ולב ידברו וז״ש ויכזב כי כזב הוא לעתיד כמו שקר לשעבר ובן אדם הם הפחותים מזה ויתנחם. ההוא אמר וכו' קאי על השם ב״ה והוא בלשון תמי' כי הה״א הוא ה״א התמי' ומהראוי היה לנקוד בחטף פתח אך כשאותיות אחה״ע באין אחריו נקוד בפתח לבד וכמו העבד ישראל (ירמי' ב' י״ד) וז״ש וכי אפשר שהשם אמר ולא יעשה כלל. ודבר ולא יקימנה ההוא אמר. על המחשבה בלב כמ״ש ויאמר אל לבו ודיבור הוא בפה ולא יקימנה וכמ״ש כי הוא אמר ויהי הוא צוה ויעמד. והוא לשון קיום הדבר שנתהווה במחשבה ויעמוד הדבר בדיבור שהדיבור מקיימו וז״ש אמר ולא יעשה ודבר ולא יקימנה:",
      "source_url": "https://www.sefaria.org/Aderet_Eliyahu,_Numbers_23:19:1"
    },
    {
      "commentator_name": "מלבי\"ם",
      "commentary_text": "לא איש התוכח עמו על שחשב שה' יתנחם ויספים שיקללם אחר שא\"ל בפעם הראשון שיברך אותם, מבאר לו שזה א\"א בחק האל ית', ויש הבדל בין שם איש ובין שם אדם, ששם איש מציין כל יש ונמצא ונופל גם על המלאכים גם על יתר נמצאים, אבל שם אדם מציין את האדם לבדו כמ\"ש בתורה אור (ויקרא סי' י') באורך, ויש הבדל בין מכזב ובין מתנחם, שהכזב הוא שהדבר אין בו ממש תכף, והנחום הוא מה שמתחרט אח\"כ. והנה אצל כל הנמצאים הגם שלא יצדק עליהם הנחום והחרטה, למשל על המלאך לא יצדק לומר שמתחרט כי אינו בעל בחירה, בכ\"ז יצדק לומר שמכזב, כי אחר שכל נמצא זולת האל ית' כחו מוגבל ובעל תכלית אם מבטיח לעשות דבר שלמעלה מכחו הוא מכזב תכף, אבל אם יאמר לעשות דבר שהוא בכחו לא יתנחם ויתחרט, אבל אצל האדם שהוא בעל בחירה ורצונו אינו רצון בלתי משתנה יצויר ג\"כ החרטה והנחום, וכמ\"ש (שמואל א ט״ו:כ״ט) וגם נצח ישראל לא ישקר ולא ינחם כי לא אדם הוא להנחם, ר\"ל שלא ישקר שהדבר שאמר יהיה כזב תכף, וגם לא ינחם שיתחרט אח\"כ על הבטחתו שזה יצויר רק אצל האדם וה' לא אדם הוא להנחם, ועז\"א מה שאתה חושב שיסכים לקללם, אם אתה חושב שמה שאמר תחלה לברכם הי' דבר כזב תכף, לא איש אל ויכזב ואם אתה חושב שאח\"כ יתחרט על דבורו הקודם אינו בן אדם שיתנחם ומפרש נגד מ\"ש לא איש אל ויכזב ההוא אמר ולא יעשה וכי כחו מוגבל עד שיצויר שיכזב תכף בשעה שאמר לעשות הדבר, שלא יהיה בכחו לעשותו, הלא אינו איש כשאר יש ונמצא שכחו מוגבל, וגם ר\"ל שתכף כשאומר לעשות דבר כבר הדבר עשוי כי אין עכוב לפניו והאמירה הוא העשיה, ונגד ולא בן אדם ויתנחם אומר הכי יצויר שדבר ולא יקימנה בעתיד ע\"י שינחם מדבורו ולא יקים את דברו אשר דבר:",
      "source_url": "https://www.sefaria.org/Malbim_on_Numbers_23:19:1"
    },
    {
      "commentator_name": "גור אריה",
      "commentary_text": "ותרגום תייבין ומתמלכין חוזרין ונמלכין. בא לפרש התרגום שאמר 'תייבין ומתמלכין', דמשמע תייבין שכבר חזרו, ואם כן מה צריך לומר 'ומתמלכין', אחר שכבר חזרו. ופירש (רש\"י) דבריו מה שאמר 'תייבין ומתמלכין', רצה לומר 'חוזרין ונמלכין', ואין 'תייבין' רוצה לומר שחוזרין מן המעשה, אלא מתחלה חשבו לעשות דבר זה בודאי, ומזה חוזרין, שאין ודאי להם לעשות, ומתמלכין אם לעשות:",
      "source_url": "https://www.sefaria.org/Gur_Aryeh_on_Bamidbar_23:19:1"
    },
    {
      "commentator_name": "נתינה לגר",
      "commentary_text": "לא איש אל ויכזב ובן אדם ויתנחם, לא כמלי בני אנשא מימר אלהא בני אנשא אמרין ומכדבין ואף לא כעובדי בני בשרא דאנון גזרין למעבד ותיבין ומתמלכין. ר\"ל לא כדברי בני אדם אמרת ה', בני אדם אומרים ומכזבים, וגם לא כמעשי אנשים שהם גוזרים לעשות ושבים ומתנחמים. לדעת המת' נופל הפעל \"כזב\" רק על השתנות הדבור, והפעל \"נחם\" על השתנות המעשה, ות' \"בני אנשא, בני בשרא\" בל\"ר להקל על הלשון.",
      "source_url": "https://www.sefaria.org/Netinah_LaGer,_Numbers_23:19:1"
    },
    {
      "commentator_name": "נתינה לגר",
      "commentary_text": "ההוא אמר ולא יעשה, דהוא אמר ועבד. הפך השאלה בדרך שלילה להחלטה בדרך חיוב כדרכו לכבוד ה' ופירוש הה\"א הראשונה שבמלת \"ההוא\" לא לה\"א התימה והשאלה, כ\"א לה\"א הידיעה, ור\"ל שהוא (הקב\"ה) אומר ועושה, גוזר ומקיים.",
      "source_url": "https://www.sefaria.org/Netinah_LaGer,_Numbers_23:19:2"
    },
    {
      "commentator_name": "אלשיך",
      "commentary_text": "לא איש אל ויכזב וכו'. ראוי לשים לב אל איזה דבר הוא אומר שלא יכזב ושלא יתנחם. ועוד כפלו כמה פעמים ענין ראש הכתוב וענין סופו. ועוד אומר הנה ברך לקחתי כי לא ברך לקח כ\"א בעל כרחו ולא עוד אלא שאומר וברך ולא אשיבנה שיורה כי חפצו לברך את ישראל והוא לא כן ידמה וכן בכל הכתובים קושיות אין מספר ומשוללי הבנה פשטיות: אמנם הנה ארז\"ל כי מה שהוליכו ראש הפסגה והוא על כי שם יאסף מרע\"ה מושיען של ישראל והעולה על רוחם כי בסלוקו של מוציאם ממצרים נסתלק זכות כניסת לארץ כי הן זה מאמר בלק כמו שאמרו ז\"ל באומר ואגרשנו מן הארץ לגרשם מן העולם בל יבואו וירשו א\"י. וע\"כ יתכן בא ויאמר משומו אל פיו לא איש וכו' לומר לא ימנע או מתחלה כשנדר להם הוא ית' ארץ ישראל היה בדעתו שלא ליתנה כי לא נעלם ממנו אשר תבקש ממנו עתה בעריכת המזבחות כי יודע העתיד הוא. או כי מאז גמר בדעתו ליתנה ועתה ע\"י מעשיך יתנחם. אם הוא החלוקה הראשונה לא איש אל ויכזב. ואם הב' ובן אדם ויתנחם. ושמא תאמר הלא מצינו וינחם ה' על הרעה לזה אמר ההוא אמר וכו' והיא תשובת ירמיה אל חנניה הנביא שהיה מתנבא שלום באמור אם כדברך לא יעדר הטוב כי הנה ית' חוזר מהרע ולא מהטוב וכמ\"ש ז\"ל שאפילו על תנאי אינו חוזר. וזה אומר פה בתמיה ההוא אמר שהוא אמירה של חיבה וטובה כטבע לשון אמירה ולא יעשה כלומר זה אי אפשר. אך ודבר שהוא ענין של קושי אז ולא יקימנה כי ניחם על הרעה באופן כי מתנת הארץ שהוא טובה לא ישוב ממנה. והראיה ממני כי מבשרי אחזה כי הנה ברך לקחתי שבראותו כונתו ית' לברך את ישראל לקחתי לעצמי לברך ברכה א' להפיק רצונו אולי אחרי כן יניחני בבחירתי להפך הדבר ולא אוכל כ\"א וברך יותר ולא אוכל להשיבה וזהו וברך ולא אשיבנה. ואין זה רק כי ה' ידבר טוב על ישראל ולא ישיב ומה גם עתה מה שדבר בפירוש. והנכון יאמר כנודע מרז\"ל כי עתידי' היו הברכות ליאמר מפי מרע\"ה ותוכחות מפי בלעם אלא אמר הקב\"ה שאין ראוי יכניע הרשע ההוא את בניו כי אם אדרבא יהיו הברכות על ידו כי מלאך רע יענה אמן בעל כרחו וכו'. בזה יאמר ראה נא חשקו ית' לברך את ישראל ממני תראה כי הנה ברך לקחתי מזולתי הוא משה כי אליו יאותו באופן שגנובות הן אתי חוץ מטבעי באופן שהיה קל להפך הברכה ועם כל זה וברך ולא אשיבנה ולא אוכל לשוב מהם כל כך ה' חפץ לברכם. ושמא תאמר כי תנאי היו דבריו במתנת הארץ אם יהיו צדיקים כאומר לזרעך אחריך אך כשחטאו ישראל במדבר עונות קשים נתבטלה הגזרה והמתנה. כי לא כן הוא כי הנה החוטאים במדבר לא צדיקי' היו הנקראי' בשם ישראל כ\"א הערב רב בעגל ואשר נמשכו אחריהם מהירודים הנקראים בשם יעקב וכן האספסוף והנקראים עם כי גם במרגלים עשרה המה אשר המסו את לבבם ועל כן לא היה כעסו ית' עצמיי. וז\"א לא הביט ולא הסתכל און שעשו הנקראים יעקב יען כי לא ראה עמל בישראל הם השלמים וכשרים הנקראים ישראל ועמל הוא עון כמ\"ש הוגעתני בעונותיך. ושמא תאמר הלא הרעים בקולו לאמר ואכלם אינו כלום כי גם ברעם קולו היו חיים וחסד בלבו כמו שאמרו ז\"ל באומר הניחה לי ויחר אפי כו' שאמר משה וכי תופס הייתי בך אלא כדי שיתפוס ויחזיק בתפלה כאב על בנו שאומר לאשר לפניו אל תעכבו בידי הניחוני שאמיתהו ומכוין שיאחזו בו ויחלו פניו לבלתי המית אותו וזה יאמר ה' אלהיו של ישראל עמו לרחמו ותרועת והגזמ' מלך בלבד הוא שהיה בו ולא לפעול הכליה חלילה. ועוד ראיה אל חיבתו ית' עליהם כי הנה אל מוציא' ממצרים וכו' והוא בשום לב אל מז\"ל בגמרא תועפות אלו מלאכי השרת ראם אלו השדים כי הלא כמו זר נחשב מי נתן בזה מלאכים ושדים אך יאמר כי הנה היה יכול הוא ית' להוציא ישראל ממצרים ע\"י מלאך או שרף שימות את המצריים כאשר בימי חזקיה את סנחרב וחילו או באחד מכחות הטומאה השדים ודומיהם אך הוא כי רצה הקב\"ה באהבת ה' את עמו בנו בכורו להוציאם ע\"י עצמו כאומר ועברתי וכו' אני ולא מלאך וכו' וזהו אל כלומר בעצמו מוציאם ממצרים עם היות כי כתועפות ראם שהם מלאכי השרת ושדים לו ית' שהיה יכול להוציאם על ידם ולא עשה כן כ\"א הוא ית' הוציאם בעצמו: או יאמר לא הביט וכו'. לומר הלא חשבת בבואך לפסגה אשר שם סילוק מרע\"ה כי בלעדו לא היו קיימים כי לולא משה וכו' עמד בפרץ היו כלים בעגל וכיוצא בו ועל כן בעשות התעוררות במקום סילוקו במערכת קרבנות תתעורר לויתן של שונאי ישראל. לא כן הוא כי מה שהם קיימים עתה גם בלעדי משה היו קיימים כי לא הביט און וכו' כדלעיל כי ה' אלהיו עמו בלי משה כן עתה בסילוקו אם משה מת ה' אלהי ישראל נשאר עמו בסלוקו. ואשר תראה הרעשת ההגזמה ההיא באומר הניחה לי וכו' שמורה שלולא משה היו כלים לא הי' דעתו ית' לכלותם לפי האמת כ\"א הרעשתו ותרועת מלך בו ולא נקמת מלך הבלתי מרחם. ושמא תאמר שאם לא היה משה לא היו יוצאים ממצרים וגם עתה יהיה להם העדר הצלחה בהתעוררות סלוקו עם מערכת המזבחות לא כן הוא כי בלעדי משה הוא ית' מוציאם. הראיה כי הנה מצרים הנזכר הוא שרו של מצרים שמצרים שמו כנודע כתועפות מלאכי השרת וראם אלו השדים לו. ואיך היה משה ב\"ו יכול להם אם לא היה הוא יתברך בעצמו עושה כל והוא היכול לשדדם:",
      "source_url": "https://www.sefaria.org/Alshekh_on_Torah,_Numbers_23:19:1-3"
    },
    {
      "commentator_name": "דברי דוד",
      "commentary_text": "ההוא אמר כו' חוזרין ונמלכין לחזור וא\"ל הא בהקב\"ה גם כן הוא דכתיב וינחם ה' על הרעה וכן רגע אדבר כו' ורגע אדבר כו', היינו מחמת שנשתנה הענין ממה שהיה תחילה כגון שעשו תשובה משא\"כ כאן שאין שינוי בישראל ולמה ינחם הקב\"ה לחזור ממה שהבטיח:",
      "source_url": "https://www.sefaria.org/Divrei_David_on_Rashi,_Numbers_23:19:1"
    },
    {
      "commentator_name": "הדר זקנים",
      "commentary_text": "לא איש ויכזב ובן אדם ויתנחם. קשה והא כתי' בפרשת בראשית כי נחמתי כי עשיתים וכן וינחם ה' כי עשה את האדם וכן וינחם ה' על הרעה. ואומר הרב\"ש כי ג' מיני נחמה הם פעמים שאדם עושה טובה או רעה ומתחרט ויש לאל ידו לעשותה זהו כזב שכוזב ופעמים שסובר שיוכל לעשותה ואין לאל ידו ובעל כרחו מתנחם מחמת אונס ועל שתיהם הוא אומר לא איש אל ויכזב אלא מקיים דברו ואף לא בן אדם ויתנחם משום שאין יכולת בידו כי הכל בידו ולא קצרה ידו. ויש נחמה שלישית שאינו בא מחמת העדר כגון אם ידבר הקב\"ה על גוי ועל ממלכה להרע כמ\"ש על נינוה. ודאי ע\"מ כן הוא או' אם יעמדו במרדם ואם יעשו תשובה ישוב מחרון אפו להטיב להם וזהו שאמ' ההוא אמ' ולא יעשה ודבר ולא יקימנה בניחותא וכן להפך ודברו אמת יתברך וישתבח שמו. וכן כתיב רגע אדבר על גוי לנתוש ולנתוץ וכו' ושב הגוי ההוא מרעתו ונחמתי על הרעה אשר חשבתי עליו ורגע אדבר על גוי לבנות ולנטוע ועשה רעה בעיני ונחמתי על הטובה ונחמה זו אינה תלויה כלל בבורא כי הקב\"ה אינו מתנחם כלל שהכל יודעים דאדעתא דהכי נדר. ונחמתי דכתיב בספר בראשית הכי קאמר אעשה עצמי כאלו נחמתי מעשייתם אמנם אין הבורא מתנחם כי אדעתא דהכי שיחטאו בגופם ובמאודם לא יצרם להעמידם. י\"מ ההוא אמר ולא יעשה בתמי' ההוא אמר ולא יעשה הקב\"ה שהוא מלך מלכי המלכים הקב\"ה אמר ולא יעשה:",
      "source_url": "https://www.sefaria.org/Hadar_Zekenim_on_Torah,_Numbers_23:19:1"
    }
  ]
}